{
  "id": "1u2cv9k",
  "name": "t3_1u2cv9k",
  "title": "Match Thread: Portugal vs Nigeria | International Friendly 2026",
  "selftext": "",
  "selftext_html": "<div class=\"md\"><h2>Portugal 0-0 Nigeria</h2> <p>Desktop note: best viewed on <a href=\"https://www.reddit.com/r/soccer/hot/\">old.reddit</a>.</p> <table><thead> <tr> <th>Info</th> <th>Details</th> </tr> </thead><tbody> <tr> <td>Competition</td> <td>2026 International Friendly</td> </tr> <tr> <td>Date</td> <td>Wed, June 10, 2026</td> </tr> <tr> <td>Venue</td> <td>Estádio Dr. Magalhães Pessoa, Leiria, Portugal</td> </tr> <tr> <td>Kickoff</td> <td>3:45 PM ET / 8:45 PM WEST</td> </tr> </tbody></table> <hr/> <p>LINE-UPS <a href=\"#sprite6-p135\"></a> Portugal (4-3-3)</p> <table><thead> <tr> <th>Starting XI</th> <th>Notes</th> <th>Subs</th> <th>Notes</th> </tr> </thead><tbody> <tr> <td><a href=\"#sprite6-p135\"></a> Diogo Costa</td> <td></td> <td><a href=\"#sprite6-p135\"></a> José Sá</td> <td></td> </tr> <tr> <td><a href=\"#sprite6-p135\"></a> Nélson Semedo</td> <td></td> <td><a href=\"#sprite6-p135\"></a> Rui Silva</td> <td></td> </tr> <tr> <td><a href=\"#sprite6-p135\"></a> Rúben Dias</td> <td></td> <td><a href=\"#sprite6-p135\"></a> Tomás Araújo</td> <td></td> </tr> <tr> <td><a href=\"#sprite6-p135\"></a> Gonçalo Inácio</td> <td></td> <td><a href=\"#sprite6-p135\"></a> João Cancelo</td> <td></td> </tr> <tr> <td><a href=\"#sprite6-p135\"></a> Diogo Dalot</td> <td></td> <td><a href=\"#sprite6-p135\"></a> Nuno Mendes</td> <td></td> </tr> <tr> <td><a href=\"#sprite6-p135\"></a> João Neves</td> <td></td> <td><a href=\"#sprite6-p135\"></a> Renato Veiga</td> <td></td> </tr> <tr> <td><a href=\"#sprite6-p135\"></a> Vitinha</td> <td></td> <td><a href=\"#sprite6-p135\"></a> Samú Costa</td> <td></td> </tr> <tr> <td><a href=\"#sprite6-p135\"></a> Bruno Fernandes</td> <td></td> <td><a href=\"#sprite6-p135\"></a> Matheus Nunes</td> <td></td> </tr> <tr> <td><a href=\"#sprite6-p135\"></a> Francisco Trincão</td> <td></td> <td><a href=\"#sprite6-p135\"></a> Rúben Neves</td> <td></td> </tr> <tr> <td><a href=\"#sprite6-p135\"></a> Cristiano Ronaldo</td> <td></td> <td><a href=\"#sprite6-p135\"></a> Bernardo Silva</td> <td></td> </tr> <tr> <td><a href=\"#sprite6-p135\"></a> Pedro Neto</td> <td></td> <td><a href=\"#sprite6-p135\"></a> Gonçalo Ramos</td> <td></td> </tr> <tr> <td></td> <td></td> <td><a href=\"#sprite6-p135\"></a> João Félix</td> <td></td> </tr> <tr> <td></td> <td></td> <td><a href=\"#sprite6-p135\"></a> Gonçalo Guedes</td> <td></td> </tr> <tr> <td></td> <td></td> <td><a href=\"#sprite6-p135\"></a> Francisco Conceição</td> <td></td> </tr> </tbody></table> <hr/> <p><a href=\"#sprite6-p124\"></a> Nigeria (4-3-3)</p> <table><thead> <tr> <th>Starting XI</th> <th>Notes</th> <th>Subs</th> <th>Notes</th> </tr> </thead><tbody> <tr> <td><a href=\"#sprite6-p124\"></a> Maduka Okoye</td> <td></td> <td><a href=\"#sprite6-p124\"></a> Francis Uzoho</td> <td></td> </tr> <tr> <td><a href=\"#sprite6-p124\"></a> Calvin Bassey</td> <td></td> <td><a href=\"#sprite6-p124\"></a> Arthur Okonkwo</td> <td></td> </tr> <tr> <td><a href=\"#sprite6-p124\"></a> Semi Ajayi</td> <td></td> <td><a href=\"#sprite6-p124\"></a> Emmanuel Fernandez</td> <td></td> </tr> <tr> <td><a href=\"#sprite6-p124\"></a> Bruno Onyemaechi</td> <td></td> <td><a href=\"#sprite6-p124\"></a> Zaidu Sanusi</td> <td></td> </tr> <tr> <td><a href=\"#sprite6-p124\"></a> Wilfred Ndidi</td> <td></td> <td><a href=\"#sprite6-p124\"></a> Bewene Abdullahi Ibrahim</td> <td></td> </tr> <tr> <td><a href=\"#sprite6-p124\"></a> Fisayo Dele-Bashiru</td> <td></td> <td><a href=\"#sprite6-p124\"></a> Frank Onyeka</td> <td></td> </tr> <tr> <td><a href=\"#sprite6-p124\"></a> Tochukwu Nnadi</td> <td></td> <td><a href=\"#sprite6-p124\"></a> Raphael Onyedika</td> <td></td> </tr> <tr> <td><a href=\"#sprite6-p124\"></a> Christian Akpan</td> <td></td> <td><a href=\"#sprite6-p124\"></a> Philip Otele</td> <td></td> </tr> <tr> <td><a href=\"#sprite6-p124\"></a> Moses Simon</td> <td></td> <td><a href=\"#sprite6-p124\"></a> Terem Moffi</td> <td></td> </tr> <tr> <td><a href=\"#sprite6-p124\"></a> Akor Adams</td> <td></td> <td><a href=\"#sprite6-p124\"></a> Paul Onuachu</td> <td></td> </tr> <tr> <td><a href=\"#sprite6-p124\"></a> Alex Iwobi</td> <td></td> <td></td> <td></td> </tr> </tbody></table> <hr/> <p>MATCH EVENTS | via ESPN</p> <h2>Kickoff</h2> <p>MATCH STATS</p> <table><thead> <tr> <th>Stat</th> <th>Portugal</th> <th>Nigeria</th> </tr> </thead><tbody> <tr> <td>Shot Attempts</td> <td>0</td> <td>0</td> </tr> <tr> <td>Shots on Target</td> <td>0</td> <td>0</td> </tr> <tr> <td>Possession</td> <td>50%</td> <td>50%</td> </tr> <tr> <td>Fouls</td> <td>0</td> <td>0</td> </tr> <tr> <td>Yellow Cards</td> <td>0</td> <td>0</td> </tr> <tr> <td>Red Cards</td> <td>0</td> <td>0</td> </tr> <tr> <td>Corner Kicks</td> <td>0</td> <td>0</td> </tr> <tr> <td>Saves</td> <td>0</td> <td>0</td> </tr> </tbody></table> <h2>MATCH IN PROGRESS</h2> </div>",
  "content_html_raw": "<!-- SC_OFF --><div class=\"md\"><h2>Portugal 0-0 Nigeria</h2> <p>Desktop note: best viewed on <a href=\"https://www.reddit.com/r/soccer/hot/\">old.reddit</a>.</p> <table><thead> <tr> <th>Info</th> <th>Details</th> </tr> </thead><tbody> <tr> <td>Competition</td> <td>2026 International Friendly</td> </tr> <tr> <td>Date</td> <td>Wed, June 10, 2026</td> </tr> <tr> <td>Venue</td> <td>Estádio Dr. Magalhães Pessoa, Leiria, Portugal</td> </tr> <tr> <td>Kickoff</td> <td>3:45 PM ET / 8:45 PM WEST</td> </tr> </tbody></table> <hr/> <p>LINE-UPS <a href=\"#sprite6-p135\"></a> Portugal (4-3-3)</p> <table><thead> <tr> <th>Starting XI</th> <th>Notes</th> <th>Subs</th> <th>Notes</th> </tr> </thead><tbody> <tr> <td><a href=\"#sprite6-p135\"></a> Diogo Costa</td> <td></td> <td><a href=\"#sprite6-p135\"></a> José Sá</td> <td></td> </tr> <tr> <td><a href=\"#sprite6-p135\"></a> Nélson Semedo</td> <td></td> <td><a href=\"#sprite6-p135\"></a> Rui Silva</td> <td></td> </tr> <tr> <td><a href=\"#sprite6-p135\"></a> Rúben Dias</td> <td></td> <td><a href=\"#sprite6-p135\"></a> Tomás Araújo</td> <td></td> </tr> <tr> <td><a href=\"#sprite6-p135\"></a> Gonçalo Inácio</td> <td></td> <td><a href=\"#sprite6-p135\"></a> João Cancelo</td> <td></td> </tr> <tr> <td><a href=\"#sprite6-p135\"></a> Diogo Dalot</td> <td></td> <td><a href=\"#sprite6-p135\"></a> Nuno Mendes</td> <td></td> </tr> <tr> <td><a href=\"#sprite6-p135\"></a> João Neves</td> <td></td> <td><a href=\"#sprite6-p135\"></a> Renato Veiga</td> <td></td> </tr> <tr> <td><a href=\"#sprite6-p135\"></a> Vitinha</td> <td></td> <td><a href=\"#sprite6-p135\"></a> Samú Costa</td> <td></td> </tr> <tr> <td><a href=\"#sprite6-p135\"></a> Bruno Fernandes</td> <td></td> <td><a href=\"#sprite6-p135\"></a> Matheus Nunes</td> <td></td> </tr> <tr> <td><a href=\"#sprite6-p135\"></a> Francisco Trincão</td> <td></td> <td><a href=\"#sprite6-p135\"></a> Rúben Neves</td> <td></td> </tr> <tr> <td><a href=\"#sprite6-p135\"></a> Cristiano Ronaldo</td> <td></td> <td><a href=\"#sprite6-p135\"></a> Bernardo Silva</td> <td></td> </tr> <tr> <td><a href=\"#sprite6-p135\"></a> Pedro Neto</td> <td></td> <td><a href=\"#sprite6-p135\"></a> Gonçalo Ramos</td> <td></td> </tr> <tr> <td></td> <td></td> <td><a href=\"#sprite6-p135\"></a> João Félix</td> <td></td> </tr> <tr> <td></td> <td></td> <td><a href=\"#sprite6-p135\"></a> Gonçalo Guedes</td> <td></td> </tr> <tr> <td></td> <td></td> <td><a href=\"#sprite6-p135\"></a> Francisco Conceição</td> <td></td> </tr> </tbody></table> <hr/> <p><a href=\"#sprite6-p124\"></a> Nigeria (4-3-3)</p> <table><thead> <tr> <th>Starting XI</th> <th>Notes</th> <th>Subs</th> <th>Notes</th> </tr> </thead><tbody> <tr> <td><a href=\"#sprite6-p124\"></a> Maduka Okoye</td> <td></td> <td><a href=\"#sprite6-p124\"></a> Francis Uzoho</td> <td></td> </tr> <tr> <td><a href=\"#sprite6-p124\"></a> Calvin Bassey</td> <td></td> <td><a href=\"#sprite6-p124\"></a> Arthur Okonkwo</td> <td></td> </tr> <tr> <td><a href=\"#sprite6-p124\"></a> Semi Ajayi</td> <td></td> <td><a href=\"#sprite6-p124\"></a> Emmanuel Fernandez</td> <td></td> </tr> <tr> <td><a href=\"#sprite6-p124\"></a> Bruno Onyemaechi</td> <td></td> <td><a href=\"#sprite6-p124\"></a> Zaidu Sanusi</td> <td></td> </tr> <tr> <td><a href=\"#sprite6-p124\"></a> Wilfred Ndidi</td> <td></td> <td><a href=\"#sprite6-p124\"></a> Bewene Abdullahi Ibrahim</td> <td></td> </tr> <tr> <td><a href=\"#sprite6-p124\"></a> Fisayo Dele-Bashiru</td> <td></td> <td><a href=\"#sprite6-p124\"></a> Frank Onyeka</td> <td></td> </tr> <tr> <td><a href=\"#sprite6-p124\"></a> Tochukwu Nnadi</td> <td></td> <td><a href=\"#sprite6-p124\"></a> Raphael Onyedika</td> <td></td> </tr> <tr> <td><a href=\"#sprite6-p124\"></a> Christian Akpan</td> <td></td> <td><a href=\"#sprite6-p124\"></a> Philip Otele</td> <td></td> </tr> <tr> <td><a href=\"#sprite6-p124\"></a> Moses Simon</td> <td></td> <td><a href=\"#sprite6-p124\"></a> Terem Moffi</td> <td></td> </tr> <tr> <td><a href=\"#sprite6-p124\"></a> Akor Adams</td> <td></td> <td><a href=\"#sprite6-p124\"></a> Paul Onuachu</td> <td></td> </tr> <tr> <td><a href=\"#sprite6-p124\"></a> Alex Iwobi</td> <td></td> <td></td> <td></td> </tr> </tbody></table> <hr/> <p>MATCH EVENTS | via ESPN</p> <h2>Kickoff</h2> <p>MATCH STATS</p> <table><thead> <tr> <th>Stat</th> <th>Portugal</th> <th>Nigeria</th> </tr> </thead><tbody> <tr> <td>Shot Attempts</td> <td>0</td> <td>0</td> </tr> <tr> <td>Shots on Target</td> <td>0</td> <td>0</td> </tr> <tr> <td>Possession</td> <td>50%</td> <td>50%</td> </tr> <tr> <td>Fouls</td> <td>0</td> <td>0</td> </tr> <tr> <td>Yellow Cards</td> <td>0</td> <td>0</td> </tr> <tr> <td>Red Cards</td> <td>0</td> <td>0</td> </tr> <tr> <td>Corner Kicks</td> <td>0</td> <td>0</td> </tr> <tr> <td>Saves</td> <td>0</td> <td>0</td> </tr> </tbody></table> <h2>MATCH IN PROGRESS</h2> </div><!-- SC_ON -->   submitted by   <a href=\"https://www.reddit.com/user/OpbrBlud\"> /u/OpbrBlud </a> <br/> <span><a href=\"https://www.reddit.com/r/soccer/comments/1u2cv9k/match_thread_portugal_vs_nigeria_international/\">[link]</a></span>   <span><a href=\"https://www.reddit.com/r/soccer/comments/1u2cv9k/match_thread_portugal_vs_nigeria_international/\">[comments]</a></span>",
  "author": "OpbrBlud",
  "author_fullname": "",
  "author_flair_text": "",
  "author_flair_css_class": "",
  "link_flair_text": "",
  "link_flair_css_class": "",
  "score": 0,
  "upvote_ratio": 0.0,
  "ups": 0,
  "downs": 0,
  "num_comments": 0,
  "created_utc": 1781121018.0,
  "created_datetime": "2026-06-10T19:50:18+00:00",
  "edited": false,
  "url": "https://www.reddit.com/r/soccer/comments/1u2cv9k/match_thread_portugal_vs_nigeria_international/",
  "permalink": "https://www.reddit.com/r/soccer/comments/1u2cv9k/match_thread_portugal_vs_nigeria_international/",
  "domain": "",
  "is_self": false,
  "is_video": false,
  "is_original_content": false,
  "over_18": false,
  "spoiler": false,
  "stickied": false,
  "distinguished": null,
  "num_crossposts": 0,
  "crosspost_parent": null,
  "total_awards_received": 0,
  "all_awardings": [],
  "thumbnail": "",
  "is_match_thread": true,
  "media_urls": [],
  "source": "rss",
  "t0_snapshot": {
    "collected_at": "2026-06-10T19:50:47.231400+00:00",
    "batch_id": "2026-06-10T19:50",
    "score": 0,
    "upvote_ratio": 0.0,
    "num_comments": 0,
    "author_flair_text": "",
    "link_flair_text": "",
    "edited": false,
    "note": "RSS mode — scores/flair unavailable at scan time"
  },
  "t48_snapshot": null,
  "comments": [],
  "collection_metadata": null
}