{
  "id": "1u0c9dc",
  "name": "t3_1u0c9dc",
  "title": "[BBC] John McGinn on the World Cup ticket prices: “I find it sad - people live for the national team, it’s their life. Those fans deserve to be there as much as we do.. football without fans is nothing”",
  "selftext": "",
  "selftext_html": "",
  "content_html_raw": "  submitted by   <a href=\"https://www.reddit.com/user/CNF1G\"> /u/CNF1G </a> <br/> <span><a href=\"https://v.redd.it/5kbwky1e136h1\">[link]</a></span>   <span><a href=\"https://www.reddit.com/r/soccer/comments/1u0c9dc/bbc_john_mcginn_on_the_world_cup_ticket_prices_i/\">[comments]</a></span>",
  "author": "CNF1G",
  "author_fullname": "",
  "author_flair_text": "",
  "author_flair_css_class": "",
  "link_flair_text": "",
  "link_flair_css_class": "",
  "score": 0,
  "upvote_ratio": 0.0,
  "ups": 0,
  "downs": 0,
  "num_comments": 0,
  "created_utc": 1780934759.0,
  "created_datetime": "2026-06-08T16:05:59+00:00",
  "edited": false,
  "url": "https://v.redd.it/5kbwky1e136h1",
  "permalink": "https://www.reddit.com/r/soccer/comments/1u0c9dc/bbc_john_mcginn_on_the_world_cup_ticket_prices_i/",
  "domain": "",
  "is_self": false,
  "is_video": false,
  "is_original_content": false,
  "over_18": false,
  "spoiler": false,
  "stickied": false,
  "distinguished": null,
  "num_crossposts": 0,
  "crosspost_parent": null,
  "total_awards_received": 0,
  "all_awardings": [],
  "thumbnail": "",
  "is_match_thread": false,
  "media_urls": [
    {
      "url": "https://v.redd.it/5kbwky1e136h1",
      "source": "external_link",
      "type": "link",
      "verified": false,
      "status_code": 403,
      "content_type": "text/html",
      "content_length": "190240",
      "final_url": "https://www.reddit.com/video/5kbwky1e136h1",
      "downloaded": false,
      "reason": "403 Client Error: Blocked for url: https://www.reddit.com/video/5kbwky1e136h1"
    }
  ],
  "source": "rss",
  "t0_snapshot": {
    "collected_at": "2026-06-08T16:08:46.383016+00:00",
    "batch_id": "2026-06-08T16",
    "score": 0,
    "upvote_ratio": 0.0,
    "num_comments": 0,
    "author_flair_text": "",
    "link_flair_text": "",
    "edited": false,
    "note": "RSS mode — scores/flair unavailable at scan time"
  },
  "t48_snapshot": {
    "collected_at": "2026-06-10T16:03:46.532576+00:00",
    "note": "RSS mode — scores/flair/deletion status unavailable"
  },
  "comments": [
    {
      "id": "oqh167r",
      "name": "t1_oqh167r",
      "author": "AutoModerator",
      "body": "",
      "body_html": "<!-- SC_OFF --><div class=\"md\"><p><strong>Mirrors / Alternative Angles</strong></p> <p><em>I am a bot, and this action was performed automatically. Please <a href=\"/message/compose/?to=/r/soccer\">contact the moderators of this subreddit</a> if you have any questions or concerns.</em></p> </div><!-- SC_ON -->",
      "created_utc": null,
      "created_datetime": null,
      "score": 0,
      "ups": 0,
      "downs": 0,
      "parent_id": "t3_1u0c9dc",
      "depth": 0,
      "author_flair_text": "",
      "author_flair_css_class": "",
      "author_fullname": "",
      "edited": false,
      "is_submitter": false,
      "distinguished": null,
      "stickied": false,
      "controversiality": 0,
      "total_awards_received": 0,
      "all_awardings": [],
      "source": "rss"
    },
    {
      "id": "oqh1i1p",
      "name": "t1_oqh1i1p",
      "author": "CNF1G",
      "body": "",
      "body_html": "<!-- SC_OFF --><div class=\"md\"><p>From Kevin Bridges’ new BBC doc called In Search of the Beautiful Game - highly recommend it </p> </div><!-- SC_ON -->",
      "created_utc": null,
      "created_datetime": null,
      "score": 0,
      "ups": 0,
      "downs": 0,
      "parent_id": "t3_1u0c9dc",
      "depth": 0,
      "author_flair_text": "",
      "author_flair_css_class": "",
      "author_fullname": "",
      "edited": false,
      "is_submitter": false,
      "distinguished": null,
      "stickied": false,
      "controversiality": 0,
      "total_awards_received": 0,
      "all_awardings": [],
      "source": "rss"
    },
    {
      "id": "oqh2rkk",
      "name": "t1_oqh2rkk",
      "author": "TheBB",
      "body": "",
      "body_html": "<!-- SC_OFF --><div class=\"md\"><p>Kevin Bridges of horse-buying fame? </p> </div><!-- SC_ON -->",
      "created_utc": null,
      "created_datetime": null,
      "score": 0,
      "ups": 0,
      "downs": 0,
      "parent_id": "t3_1u0c9dc",
      "depth": 0,
      "author_flair_text": "",
      "author_flair_css_class": "",
      "author_fullname": "",
      "edited": false,
      "is_submitter": false,
      "distinguished": null,
      "stickied": false,
      "controversiality": 0,
      "total_awards_received": 0,
      "all_awardings": [],
      "source": "rss"
    },
    {
      "id": "oqhdw9p",
      "name": "t1_oqhdw9p",
      "author": "noodlesalad_",
      "body": "",
      "body_html": "<!-- SC_OFF --><div class=\"md\"><p><a href=\"https://youtu.be/Yl0cnAGThM0\">For anyone lucky enough not to have seen it yet</a></p> </div><!-- SC_ON -->",
      "created_utc": null,
      "created_datetime": null,
      "score": 0,
      "ups": 0,
      "downs": 0,
      "parent_id": "t3_1u0c9dc",
      "depth": 0,
      "author_flair_text": "",
      "author_flair_css_class": "",
      "author_fullname": "",
      "edited": false,
      "is_submitter": false,
      "distinguished": null,
      "stickied": false,
      "controversiality": 0,
      "total_awards_received": 0,
      "all_awardings": [],
      "source": "rss"
    },
    {
      "id": "oqhhgpm",
      "name": "t1_oqhhgpm",
      "author": "Moist_Transition_755",
      "body": "",
      "body_html": "<!-- SC_OFF --><div class=\"md\"><p>Wish I could watch it again for the first time.</p> </div><!-- SC_ON -->",
      "created_utc": null,
      "created_datetime": null,
      "score": 0,
      "ups": 0,
      "downs": 0,
      "parent_id": "t3_1u0c9dc",
      "depth": 0,
      "author_flair_text": "",
      "author_flair_css_class": "",
      "author_fullname": "",
      "edited": false,
      "is_submitter": false,
      "distinguished": null,
      "stickied": false,
      "controversiality": 0,
      "total_awards_received": 0,
      "all_awardings": [],
      "source": "rss"
    },
    {
      "id": "oqhknx2",
      "name": "t1_oqhknx2",
      "author": "LeftWingScot",
      "body": "",
      "body_html": "<!-- SC_OFF --><div class=\"md\"><p>I wish i was there for the recording.</p> <p>from what i've heard it was utter chaos and took a ridiculously long time to record a segment which didn't even last 8 minutes. </p> <p>Cast just kept breaking down in laughter at the ridiculousness of his story and Lee Macks jokes.</p> </div><!-- SC_ON -->",
      "created_utc": null,
      "created_datetime": null,
      "score": 0,
      "ups": 0,
      "downs": 0,
      "parent_id": "t3_1u0c9dc",
      "depth": 0,
      "author_flair_text": "",
      "author_flair_css_class": "",
      "author_fullname": "",
      "edited": false,
      "is_submitter": false,
      "distinguished": null,
      "stickied": false,
      "controversiality": 0,
      "total_awards_received": 0,
      "all_awardings": [],
      "source": "rss"
    },
    {
      "id": "oqi4791",
      "name": "t1_oqi4791",
      "author": "Wuktrio",
      "body": "",
      "body_html": "<!-- SC_OFF --><div class=\"md\"><p>You notice they had to cut away stuff, because there's suddenly locals telling him to go away, which he never mentions haha</p> </div><!-- SC_ON -->",
      "created_utc": null,
      "created_datetime": null,
      "score": 0,
      "ups": 0,
      "downs": 0,
      "parent_id": "t3_1u0c9dc",
      "depth": 0,
      "author_flair_text": "",
      "author_flair_css_class": "",
      "author_fullname": "",
      "edited": false,
      "is_submitter": false,
      "distinguished": null,
      "stickied": false,
      "controversiality": 0,
      "total_awards_received": 0,
      "all_awardings": [],
      "source": "rss"
    },
    {
      "id": "oqh4tj1",
      "name": "t1_oqh4tj1",
      "author": "CNF1G",
      "body": "",
      "body_html": "<!-- SC_OFF --><div class=\"md\"><p>The one and only</p> </div><!-- SC_ON -->",
      "created_utc": null,
      "created_datetime": null,
      "score": 0,
      "ups": 0,
      "downs": 0,
      "parent_id": "t3_1u0c9dc",
      "depth": 0,
      "author_flair_text": "",
      "author_flair_css_class": "",
      "author_fullname": "",
      "edited": false,
      "is_submitter": false,
      "distinguished": null,
      "stickied": false,
      "controversiality": 0,
      "total_awards_received": 0,
      "all_awardings": [],
      "source": "rss"
    },
    {
      "id": "oqhzo6q",
      "name": "t1_oqhzo6q",
      "author": "wtfakb",
      "body": "",
      "body_html": "<!-- SC_OFF --><div class=\"md\"><p>WILTY, Scotland football, Celtic. All my passions combined</p> </div><!-- SC_ON -->",
      "created_utc": null,
      "created_datetime": null,
      "score": 0,
      "ups": 0,
      "downs": 0,
      "parent_id": "t3_1u0c9dc",
      "depth": 0,
      "author_flair_text": "",
      "author_flair_css_class": "",
      "author_fullname": "",
      "edited": false,
      "is_submitter": false,
      "distinguished": null,
      "stickied": false,
      "controversiality": 0,
      "total_awards_received": 0,
      "all_awardings": [],
      "source": "rss"
    },
    {
      "id": "oqh4tkw",
      "name": "t1_oqh4tkw",
      "author": "Practical_Phrase_721",
      "body": "",
      "body_html": "<!-- SC_OFF --><div class=\"md\"><p>Damn right! 😂</p> </div><!-- SC_ON -->",
      "created_utc": null,
      "created_datetime": null,
      "score": 0,
      "ups": 0,
      "downs": 0,
      "parent_id": "t3_1u0c9dc",
      "depth": 0,
      "author_flair_text": "",
      "author_flair_css_class": "",
      "author_fullname": "",
      "edited": false,
      "is_submitter": false,
      "distinguished": null,
      "stickied": false,
      "controversiality": 0,
      "total_awards_received": 0,
      "all_awardings": [],
      "source": "rss"
    },
    {
      "id": "oqia3yq",
      "name": "t1_oqia3yq",
      "author": "Finbarr-Galedeep",
      "body": "",
      "body_html": "<!-- SC_OFF --><div class=\"md\"><p>Exclusively accidental horse-buying though.</p> </div><!-- SC_ON -->",
      "created_utc": null,
      "created_datetime": null,
      "score": 0,
      "ups": 0,
      "downs": 0,
      "parent_id": "t3_1u0c9dc",
      "depth": 0,
      "author_flair_text": "",
      "author_flair_css_class": "",
      "author_fullname": "",
      "edited": false,
      "is_submitter": false,
      "distinguished": null,
      "stickied": false,
      "controversiality": 0,
      "total_awards_received": 0,
      "all_awardings": [],
      "source": "rss"
    },
    {
      "id": "oqh7pjj",
      "name": "t1_oqh7pjj",
      "author": "sheikh_n_bake",
      "body": "",
      "body_html": "<!-- SC_OFF --><div class=\"md\"><p>Slapping it on the iPlayer now, cheers mate.</p> <p>It starts with Dario G 🔥 so you know it'll be good</p> </div><!-- SC_ON -->",
      "created_utc": null,
      "created_datetime": null,
      "score": 0,
      "ups": 0,
      "downs": 0,
      "parent_id": "t3_1u0c9dc",
      "depth": 0,
      "author_flair_text": "",
      "author_flair_css_class": "",
      "author_fullname": "",
      "edited": false,
      "is_submitter": false,
      "distinguished": null,
      "stickied": false,
      "controversiality": 0,
      "total_awards_received": 0,
      "all_awardings": [],
      "source": "rss"
    },
    {
      "id": "oqivqco",
      "name": "t1_oqivqco",
      "author": "FatRascal_",
      "body": "",
      "body_html": "<!-- SC_OFF --><div class=\"md\"><p>“Football without cans is nothing” </p> </div><!-- SC_ON -->",
      "created_utc": null,
      "created_datetime": null,
      "score": 0,
      "ups": 0,
      "downs": 0,
      "parent_id": "t3_1u0c9dc",
      "depth": 0,
      "author_flair_text": "",
      "author_flair_css_class": "",
      "author_fullname": "",
      "edited": false,
      "is_submitter": false,
      "distinguished": null,
      "stickied": false,
      "controversiality": 0,
      "total_awards_received": 0,
      "all_awardings": [],
      "source": "rss"
    },
    {
      "id": "oqmlt4l",
      "name": "t1_oqmlt4l",
      "author": "nospellingerorrs",
      "body": "",
      "body_html": "<!-- SC_OFF --><div class=\"md\"><p>Was a cracking doc. The Sao Paolo game looked fun.</p> </div><!-- SC_ON -->",
      "created_utc": null,
      "created_datetime": null,
      "score": 0,
      "ups": 0,
      "downs": 0,
      "parent_id": "t3_1u0c9dc",
      "depth": 0,
      "author_flair_text": "",
      "author_flair_css_class": "",
      "author_fullname": "",
      "edited": false,
      "is_submitter": false,
      "distinguished": null,
      "stickied": false,
      "controversiality": 0,
      "total_awards_received": 0,
      "all_awardings": [],
      "source": "rss"
    },
    {
      "id": "oqh3mcq",
      "name": "t1_oqh3mcq",
      "author": "n22rwrdr",
      "body": "",
      "body_html": "<!-- SC_OFF --><div class=\"md\"><p>What McGinn doesn’t understand is that we don’t care about legacy fans. It’s all about shareholders value. </p> </div><!-- SC_ON -->",
      "created_utc": null,
      "created_datetime": null,
      "score": 0,
      "ups": 0,
      "downs": 0,
      "parent_id": "t3_1u0c9dc",
      "depth": 0,
      "author_flair_text": "",
      "author_flair_css_class": "",
      "author_fullname": "",
      "edited": false,
      "is_submitter": false,
      "distinguished": null,
      "stickied": false,
      "controversiality": 0,
      "total_awards_received": 0,
      "all_awardings": [],
      "source": "rss"
    },
    {
      "id": "oqh631v",
      "name": "t1_oqh631v",
      "author": "Big-Raspberry-6151",
      "body": "",
      "body_html": "<!-- SC_OFF --><div class=\"md\"><p>Infantino: \"thank you finally someone gets it\"</p> </div><!-- SC_ON -->",
      "created_utc": null,
      "created_datetime": null,
      "score": 0,
      "ups": 0,
      "downs": 0,
      "parent_id": "t3_1u0c9dc",
      "depth": 0,
      "author_flair_text": "",
      "author_flair_css_class": "",
      "author_fullname": "",
      "edited": false,
      "is_submitter": false,
      "distinguished": null,
      "stickied": false,
      "controversiality": 0,
      "total_awards_received": 0,
      "all_awardings": [],
      "source": "rss"
    },
    {
      "id": "oqhgn2d",
      "name": "t1_oqhgn2d",
      "author": "abactore",
      "body": "",
      "body_html": "<!-- SC_OFF --><div class=\"md\"><p>Exactly!</p> <p>Human and communal experiences are ultimately not important. What really matters is watching a number on a screen go up really high📈</p> </div><!-- SC_ON -->",
      "created_utc": null,
      "created_datetime": null,
      "score": 0,
      "ups": 0,
      "downs": 0,
      "parent_id": "t3_1u0c9dc",
      "depth": 0,
      "author_flair_text": "",
      "author_flair_css_class": "",
      "author_fullname": "",
      "edited": false,
      "is_submitter": false,
      "distinguished": null,
      "stickied": false,
      "controversiality": 0,
      "total_awards_received": 0,
      "all_awardings": [],
      "source": "rss"
    },
    {
      "id": "oqhzw1p",
      "name": "t1_oqhzw1p",
      "author": "n22rwrdr",
      "body": "",
      "body_html": "<!-- SC_OFF --><div class=\"md\"><p>Does anyone ever think about their KPI’s? </p> </div><!-- SC_ON -->",
      "created_utc": null,
      "created_datetime": null,
      "score": 0,
      "ups": 0,
      "downs": 0,
      "parent_id": "t3_1u0c9dc",
      "depth": 0,
      "author_flair_text": "",
      "author_flair_css_class": "",
      "author_fullname": "",
      "edited": false,
      "is_submitter": false,
      "distinguished": null,
      "stickied": false,
      "controversiality": 0,
      "total_awards_received": 0,
      "all_awardings": [],
      "source": "rss"
    },
    {
      "id": "oqibpfq",
      "name": "t1_oqibpfq",
      "author": "WhenWeTalkAboutLove",
      "body": "",
      "body_html": "<!-- SC_OFF --><div class=\"md\"><p>What even is that? I need to know before I can prioritize it over joy and human connection </p> </div><!-- SC_ON -->",
      "created_utc": null,
      "created_datetime": null,
      "score": 0,
      "ups": 0,
      "downs": 0,
      "parent_id": "t3_1u0c9dc",
      "depth": 0,
      "author_flair_text": "",
      "author_flair_css_class": "",
      "author_fullname": "",
      "edited": false,
      "is_submitter": false,
      "distinguished": null,
      "stickied": false,
      "controversiality": 0,
      "total_awards_received": 0,
      "all_awardings": [],
      "source": "rss"
    },
    {
      "id": "oql77ng",
      "name": "t1_oql77ng",
      "author": "CFDyce",
      "body": "",
      "body_html": "<!-- SC_OFF --><div class=\"md\"><p>That's what got me into football as a wee lad, shareholders value!</p> </div><!-- SC_ON -->",
      "created_utc": null,
      "created_datetime": null,
      "score": 0,
      "ups": 0,
      "downs": 0,
      "parent_id": "t3_1u0c9dc",
      "depth": 0,
      "author_flair_text": "",
      "author_flair_css_class": "",
      "author_fullname": "",
      "edited": false,
      "is_submitter": false,
      "distinguished": null,
      "stickied": false,
      "controversiality": 0,
      "total_awards_received": 0,
      "all_awardings": [],
      "source": "rss"
    },
    {
      "id": "oqhg8l1",
      "name": "t1_oqhg8l1",
      "author": "noodlesalad_",
      "body": "",
      "body_html": "<!-- SC_OFF --><div class=\"md\"><p>Line goes up is their sport</p> </div><!-- SC_ON -->",
      "created_utc": null,
      "created_datetime": null,
      "score": 0,
      "ups": 0,
      "downs": 0,
      "parent_id": "t3_1u0c9dc",
      "depth": 0,
      "author_flair_text": "",
      "author_flair_css_class": "",
      "author_fullname": "",
      "edited": false,
      "is_submitter": false,
      "distinguished": null,
      "stickied": false,
      "controversiality": 0,
      "total_awards_received": 0,
      "all_awardings": [],
      "source": "rss"
    },
    {
      "id": "oqh7cvo",
      "name": "t1_oqh7cvo",
      "author": "wh11",
      "body": "",
      "body_html": "<!-- SC_OFF --><div class=\"md\"><p>Live events are the new status symbol flex. Physical goods are losing their status due to luxury brands diluting their brand and pushing towards the middle class and dupes are becoming more and more common. You can't dupe a live event though so it's become the ultimate time+money flex for the ultra wealthy. Look at tickets to the Knicks NBA finals games. It's absurd and bleeding into all sports now</p> </div><!-- SC_ON -->",
      "created_utc": null,
      "created_datetime": null,
      "score": 0,
      "ups": 0,
      "downs": 0,
      "parent_id": "t3_1u0c9dc",
      "depth": 0,
      "author_flair_text": "",
      "author_flair_css_class": "",
      "author_fullname": "",
      "edited": false,
      "is_submitter": false,
      "distinguished": null,
      "stickied": false,
      "controversiality": 0,
      "total_awards_received": 0,
      "all_awardings": [],
      "source": "rss"
    },
    {
      "id": "oqhjggf",
      "name": "t1_oqhjggf",
      "author": "quilllord",
      "body": "",
      "body_html": "<!-- SC_OFF --><div class=\"md\"><p>wasn't football and baseballs whole gimmick that they were working class sports </p> </div><!-- SC_ON -->",
      "created_utc": null,
      "created_datetime": null,
      "score": 0,
      "ups": 0,
      "downs": 0,
      "parent_id": "t3_1u0c9dc",
      "depth": 0,
      "author_flair_text": "",
      "author_flair_css_class": "",
      "author_fullname": "",
      "edited": false,
      "is_submitter": false,
      "distinguished": null,
      "stickied": false,
      "controversiality": 0,
      "total_awards_received": 0,
      "all_awardings": [],
      "source": "rss"
    },
    {
      "id": "oqiduzd",
      "name": "t1_oqiduzd",
      "author": "WhenWeTalkAboutLove",
      "body": "",
      "body_html": "<!-- SC_OFF --><div class=\"md\"><p>Funny enough, the people in charge use that to market it to other people who buy the rest of us out of our chance to go</p> </div><!-- SC_ON -->",
      "created_utc": null,
      "created_datetime": null,
      "score": 0,
      "ups": 0,
      "downs": 0,
      "parent_id": "t3_1u0c9dc",
      "depth": 0,
      "author_flair_text": "",
      "author_flair_css_class": "",
      "author_fullname": "",
      "edited": false,
      "is_submitter": false,
      "distinguished": null,
      "stickied": false,
      "controversiality": 0,
      "total_awards_received": 0,
      "all_awardings": [],
      "source": "rss"
    },
    {
      "id": "oqjsctl",
      "name": "t1_oqjsctl",
      "author": "congeal",
      "body": "",
      "body_html": "<!-- SC_OFF --><div class=\"md\"><p>baseball is still super cheap to attend and MLS games are also cheap</p> <p>but FIFA is making these games waaaaaay too expensive for everyone</p> </div><!-- SC_ON -->",
      "created_utc": null,
      "created_datetime": null,
      "score": 0,
      "ups": 0,
      "downs": 0,
      "parent_id": "t3_1u0c9dc",
      "depth": 0,
      "author_flair_text": "",
      "author_flair_css_class": "",
      "author_fullname": "",
      "edited": false,
      "is_submitter": false,
      "distinguished": null,
      "stickied": false,
      "controversiality": 0,
      "total_awards_received": 0,
      "all_awardings": [],
      "source": "rss"
    },
    {
      "id": "oqqkxdg",
      "name": "t1_oqqkxdg",
      "author": "oscarx-ray",
      "body": "",
      "body_html": "<!-- SC_OFF --><div class=\"md\"><p>They were until they became popular and the people in charge could milk the working > middle > upper class for every penny.</p> </div><!-- SC_ON -->",
      "created_utc": null,
      "created_datetime": null,
      "score": 0,
      "ups": 0,
      "downs": 0,
      "parent_id": "t3_1u0c9dc",
      "depth": 0,
      "author_flair_text": "",
      "author_flair_css_class": "",
      "author_fullname": "",
      "edited": false,
      "is_submitter": false,
      "distinguished": null,
      "stickied": false,
      "controversiality": 0,
      "total_awards_received": 0,
      "all_awardings": [],
      "source": "rss"
    },
    {
      "id": "oqidnbp",
      "name": "t1_oqidnbp",
      "author": "WhenWeTalkAboutLove",
      "body": "",
      "body_html": "<!-- SC_OFF --><div class=\"md\"><p>This is sadly a good point, especially with the phase of social media we're in. Posting a picture of yourself at these things is really important to a lot of people especially in the population that can afford it. </p> </div><!-- SC_ON -->",
      "created_utc": null,
      "created_datetime": null,
      "score": 0,
      "ups": 0,
      "downs": 0,
      "parent_id": "t3_1u0c9dc",
      "depth": 0,
      "author_flair_text": "",
      "author_flair_css_class": "",
      "author_fullname": "",
      "edited": false,
      "is_submitter": false,
      "distinguished": null,
      "stickied": false,
      "controversiality": 0,
      "total_awards_received": 0,
      "all_awardings": [],
      "source": "rss"
    },
    {
      "id": "oqj3fgg",
      "name": "t1_oqj3fgg",
      "author": "johnnygrant",
      "body": "",
      "body_html": "<!-- SC_OFF --><div class=\"md\"><p>the prices are not worth it. </p> <p>I'd rather have a bomb ass vacation for $5000, than pay that for almost any live sport event.</p> </div><!-- SC_ON -->",
      "created_utc": null,
      "created_datetime": null,
      "score": 0,
      "ups": 0,
      "downs": 0,
      "parent_id": "t3_1u0c9dc",
      "depth": 0,
      "author_flair_text": "",
      "author_flair_css_class": "",
      "author_fullname": "",
      "edited": false,
      "is_submitter": false,
      "distinguished": null,
      "stickied": false,
      "controversiality": 0,
      "total_awards_received": 0,
      "all_awardings": [],
      "source": "rss"
    },
    {
      "id": "oqhb621",
      "name": "t1_oqhb621",
      "author": "TriceCreamSundae",
      "body": "",
      "body_html": "<!-- SC_OFF --><div class=\"md\"><p>We’re at peak “the rich dgaf” culture worldwide right now, everything is for them, nothing is for us. Why? Because we accept it. Things won’t change on their own. </p> </div><!-- SC_ON -->",
      "created_utc": null,
      "created_datetime": null,
      "score": 0,
      "ups": 0,
      "downs": 0,
      "parent_id": "t3_1u0c9dc",
      "depth": 0,
      "author_flair_text": "",
      "author_flair_css_class": "",
      "author_fullname": "",
      "edited": false,
      "is_submitter": false,
      "distinguished": null,
      "stickied": false,
      "controversiality": 0,
      "total_awards_received": 0,
      "all_awardings": [],
      "source": "rss"
    },
    {
      "id": "oqqwcn8",
      "name": "t1_oqqwcn8",
      "author": "onepingonlypleashe",
      "body": "",
      "body_html": "<!-- SC_OFF --><div class=\"md\"><p>France has entered the chat.</p> </div><!-- SC_ON -->",
      "created_utc": null,
      "created_datetime": null,
      "score": 0,
      "ups": 0,
      "downs": 0,
      "parent_id": "t3_1u0c9dc",
      "depth": 0,
      "author_flair_text": "",
      "author_flair_css_class": "",
      "author_fullname": "",
      "edited": false,
      "is_submitter": false,
      "distinguished": null,
      "stickied": false,
      "controversiality": 0,
      "total_awards_received": 0,
      "all_awardings": [],
      "source": "rss"
    },
    {
      "id": "oqt983f",
      "name": "t1_oqt983f",
      "author": "TriceCreamSundae",
      "body": "",
      "body_html": "<!-- SC_OFF --><div class=\"md\"><p>I wish </p> </div><!-- SC_ON -->",
      "created_utc": null,
      "created_datetime": null,
      "score": 0,
      "ups": 0,
      "downs": 0,
      "parent_id": "t3_1u0c9dc",
      "depth": 0,
      "author_flair_text": "",
      "author_flair_css_class": "",
      "author_fullname": "",
      "edited": false,
      "is_submitter": false,
      "distinguished": null,
      "stickied": false,
      "controversiality": 0,
      "total_awards_received": 0,
      "all_awardings": [],
      "source": "rss"
    },
    {
      "id": "oqka3kl",
      "name": "t1_oqka3kl",
      "author": "Hot-Job-6281",
      "body": "",
      "body_html": "<!-- SC_OFF --><div class=\"md\"><p>Peak? Lol. <strong>Always</strong> has been. </p> </div><!-- SC_ON -->",
      "created_utc": null,
      "created_datetime": null,
      "score": 0,
      "ups": 0,
      "downs": 0,
      "parent_id": "t3_1u0c9dc",
      "depth": 0,
      "author_flair_text": "",
      "author_flair_css_class": "",
      "author_fullname": "",
      "edited": false,
      "is_submitter": false,
      "distinguished": null,
      "stickied": false,
      "controversiality": 0,
      "total_awards_received": 0,
      "all_awardings": [],
      "source": "rss"
    },
    {
      "id": "oqmau2h",
      "name": "t1_oqmau2h",
      "author": "lllllaaaaabbbbb",
      "body": "",
      "body_html": "<!-- SC_OFF --><div class=\"md\"><p>They got scared for a bit in the 20th century after some Russian blokes got a bit rowdy</p> </div><!-- SC_ON -->",
      "created_utc": null,
      "created_datetime": null,
      "score": 0,
      "ups": 0,
      "downs": 0,
      "parent_id": "t3_1u0c9dc",
      "depth": 0,
      "author_flair_text": "",
      "author_flair_css_class": "",
      "author_fullname": "",
      "edited": false,
      "is_submitter": false,
      "distinguished": null,
      "stickied": false,
      "controversiality": 0,
      "total_awards_received": 0,
      "all_awardings": [],
      "source": "rss"
    },
    {
      "id": "oqian5c",
      "name": "t1_oqian5c",
      "author": "Finbarr-Galedeep",
      "body": "",
      "body_html": "<!-- SC_OFF --><div class=\"md\"><p>Doesn't matter if we \"accept\" it or not, we can't do anything about it.</p> </div><!-- SC_ON -->",
      "created_utc": null,
      "created_datetime": null,
      "score": 0,
      "ups": 0,
      "downs": 0,
      "parent_id": "t3_1u0c9dc",
      "depth": 0,
      "author_flair_text": "",
      "author_flair_css_class": "",
      "author_fullname": "",
      "edited": false,
      "is_submitter": false,
      "distinguished": null,
      "stickied": false,
      "controversiality": 0,
      "total_awards_received": 0,
      "all_awardings": [],
      "source": "rss"
    },
    {
      "id": "oqj6wrd",
      "name": "t1_oqj6wrd",
      "author": "UCanBdoWatWeWant2Do",
      "body": "",
      "body_html": "<!-- SC_OFF --><div class=\"md\"><p>We can. This attitude is why nothing changes.</p> </div><!-- SC_ON -->",
      "created_utc": null,
      "created_datetime": null,
      "score": 0,
      "ups": 0,
      "downs": 0,
      "parent_id": "t3_1u0c9dc",
      "depth": 0,
      "author_flair_text": "",
      "author_flair_css_class": "",
      "author_fullname": "",
      "edited": false,
      "is_submitter": false,
      "distinguished": null,
      "stickied": false,
      "controversiality": 0,
      "total_awards_received": 0,
      "all_awardings": [],
      "source": "rss"
    },
    {
      "id": "oqks0nx",
      "name": "t1_oqks0nx",
      "author": "Finbarr-Galedeep",
      "body": "",
      "body_html": "<!-- SC_OFF --><div class=\"md\"><p>Unfortunately, the rich who don't want things to change have a private army on their side called \"The Police\".</p> </div><!-- SC_ON -->",
      "created_utc": null,
      "created_datetime": null,
      "score": 0,
      "ups": 0,
      "downs": 0,
      "parent_id": "t3_1u0c9dc",
      "depth": 0,
      "author_flair_text": "",
      "author_flair_css_class": "",
      "author_fullname": "",
      "edited": false,
      "is_submitter": false,
      "distinguished": null,
      "stickied": false,
      "controversiality": 0,
      "total_awards_received": 0,
      "all_awardings": [],
      "source": "rss"
    },
    {
      "id": "oql4c9x",
      "name": "t1_oql4c9x",
      "author": "AxFairy",
      "body": "",
      "body_html": "<!-- SC_OFF --><div class=\"md\"><p>I bet you a hundred redditors could take out a cop!</p> </div><!-- SC_ON -->",
      "created_utc": null,
      "created_datetime": null,
      "score": 0,
      "ups": 0,
      "downs": 0,
      "parent_id": "t3_1u0c9dc",
      "depth": 0,
      "author_flair_text": "",
      "author_flair_css_class": "",
      "author_fullname": "",
      "edited": false,
      "is_submitter": false,
      "distinguished": null,
      "stickied": false,
      "controversiality": 0,
      "total_awards_received": 0,
      "all_awardings": [],
      "source": "rss"
    },
    {
      "id": "oqmldrc",
      "name": "t1_oqmldrc",
      "author": "nospellingerorrs",
      "body": "",
      "body_html": "<!-- SC_OFF --><div class=\"md\"><p>If this world cup sets a precedent and regular fans never get to go to a world cup ever again then the only thing to do is for fans to form a new football association, let FIFA die the death its corruption and greed deserves.</p> <p>This would involve a lot of self organisation and working together though which I don't think people are capable of anymore. </p> <p>Start following rugby I guess? <em>shudders</em> </p> </div><!-- SC_ON -->",
      "created_utc": null,
      "created_datetime": null,
      "score": 0,
      "ups": 0,
      "downs": 0,
      "parent_id": "t3_1u0c9dc",
      "depth": 0,
      "author_flair_text": "",
      "author_flair_css_class": "",
      "author_fullname": "",
      "edited": false,
      "is_submitter": false,
      "distinguished": null,
      "stickied": false,
      "controversiality": 0,
      "total_awards_received": 0,
      "all_awardings": [],
      "source": "rss"
    },
    {
      "id": "oqhh4ne",
      "name": "t1_oqhh4ne",
      "author": "KenDTree",
      "body": "",
      "body_html": "<!-- SC_OFF --><div class=\"md\"><p>Imagine they cancel his visa after seeing this</p> </div><!-- SC_ON -->",
      "created_utc": null,
      "created_datetime": null,
      "score": 0,
      "ups": 0,
      "downs": 0,
      "parent_id": "t3_1u0c9dc",
      "depth": 0,
      "author_flair_text": "",
      "author_flair_css_class": "",
      "author_fullname": "",
      "edited": false,
      "is_submitter": false,
      "distinguished": null,
      "stickied": false,
      "controversiality": 0,
      "total_awards_received": 0,
      "all_awardings": [],
      "source": "rss"
    },
    {
      "id": "oqhusqi",
      "name": "t1_oqhusqi",
      "author": "quonne",
      "body": "",
      "body_html": "<!-- SC_OFF --><div class=\"md\"><p>Straight to jail. </p> </div><!-- SC_ON -->",
      "created_utc": null,
      "created_datetime": null,
      "score": 0,
      "ups": 0,
      "downs": 0,
      "parent_id": "t3_1u0c9dc",
      "depth": 0,
      "author_flair_text": "",
      "author_flair_css_class": "",
      "author_fullname": "",
      "edited": false,
      "is_submitter": false,
      "distinguished": null,
      "stickied": false,
      "controversiality": 0,
      "total_awards_received": 0,
      "all_awardings": [],
      "source": "rss"
    },
    {
      "id": "oqj751o",
      "name": "t1_oqj751o",
      "author": "Aenjeprekemaluci",
      "body": "",
      "body_html": "<!-- SC_OFF --><div class=\"md\"><p>ICE will be called. </p> </div><!-- SC_ON -->",
      "created_utc": null,
      "created_datetime": null,
      "score": 0,
      "ups": 0,
      "downs": 0,
      "parent_id": "t3_1u0c9dc",
      "depth": 0,
      "author_flair_text": "",
      "author_flair_css_class": "",
      "author_fullname": "",
      "edited": false,
      "is_submitter": false,
      "distinguished": null,
      "stickied": false,
      "controversiality": 0,
      "total_awards_received": 0,
      "all_awardings": [],
      "source": "rss"
    },
    {
      "id": "oqh5dyr",
      "name": "t1_oqh5dyr",
      "author": "GameplayerStu",
      "body": "",
      "body_html": "<!-- SC_OFF --><div class=\"md\"><p>My fucking captain</p> </div><!-- SC_ON -->",
      "created_utc": null,
      "created_datetime": null,
      "score": 0,
      "ups": 0,
      "downs": 0,
      "parent_id": "t3_1u0c9dc",
      "depth": 0,
      "author_flair_text": "",
      "author_flair_css_class": "",
      "author_fullname": "",
      "edited": false,
      "is_submitter": false,
      "distinguished": null,
      "stickied": false,
      "controversiality": 0,
      "total_awards_received": 0,
      "all_awardings": [],
      "source": "rss"
    },
    {
      "id": "oqit3o5",
      "name": "t1_oqit3o5",
      "author": "heeleyman",
      "body": "",
      "body_html": "<!-- SC_OFF --><div class=\"md\"><p>Honestly feel sorry for fans who don't support a team captained by John McGinn. I'm biased but I can't think of a more likeable player?</p> </div><!-- SC_ON -->",
      "created_utc": null,
      "created_datetime": null,
      "score": 0,
      "ups": 0,
      "downs": 0,
      "parent_id": "t3_1u0c9dc",
      "depth": 0,
      "author_flair_text": "",
      "author_flair_css_class": "",
      "author_fullname": "",
      "edited": false,
      "is_submitter": false,
      "distinguished": null,
      "stickied": false,
      "controversiality": 0,
      "total_awards_received": 0,
      "all_awardings": [],
      "source": "rss"
    },
    {
      "id": "oqh5s9j",
      "name": "t1_oqh5s9j",
      "author": "Hour_Raisin_4547",
      "body": "",
      "body_html": "<!-- SC_OFF --><div class=\"md\"><p>It takes so much courage to make such a statement. He’s really setting the example </p> </div><!-- SC_ON -->",
      "created_utc": null,
      "created_datetime": null,
      "score": 0,
      "ups": 0,
      "downs": 0,
      "parent_id": "t3_1u0c9dc",
      "depth": 0,
      "author_flair_text": "",
      "author_flair_css_class": "",
      "author_fullname": "",
      "edited": false,
      "is_submitter": false,
      "distinguished": null,
      "stickied": false,
      "controversiality": 0,
      "total_awards_received": 0,
      "all_awardings": [],
      "source": "rss"
    },
    {
      "id": "oqhf489",
      "name": "t1_oqhf489",
      "author": "celld",
      "body": "",
      "body_html": "<!-- SC_OFF --><div class=\"md\"><p>It doesn't take much courage at all but it does need to be said. Most normal people will share the same opinion and be willing to let it be known. Most footballers come from relatively normal and mostly working class backgrounds so it's no surprise he has the only correct opinion on this.</p> </div><!-- SC_ON -->",
      "created_utc": null,
      "created_datetime": null,
      "score": 0,
      "ups": 0,
      "downs": 0,
      "parent_id": "t3_1u0c9dc",
      "depth": 0,
      "author_flair_text": "",
      "author_flair_css_class": "",
      "author_fullname": "",
      "edited": false,
      "is_submitter": false,
      "distinguished": null,
      "stickied": false,
      "controversiality": 0,
      "total_awards_received": 0,
      "all_awardings": [],
      "source": "rss"
    },
    {
      "id": "oqmlnz1",
      "name": "t1_oqmlnz1",
      "author": "nospellingerorrs",
      "body": "",
      "body_html": "<!-- SC_OFF --><div class=\"md\"><p>It doesn't take courage. It just takes giving a shit. Sadly many players won't. </p> </div><!-- SC_ON -->",
      "created_utc": null,
      "created_datetime": null,
      "score": 0,
      "ups": 0,
      "downs": 0,
      "parent_id": "t3_1u0c9dc",
      "depth": 0,
      "author_flair_text": "",
      "author_flair_css_class": "",
      "author_fullname": "",
      "edited": false,
      "is_submitter": false,
      "distinguished": null,
      "stickied": false,
      "controversiality": 0,
      "total_awards_received": 0,
      "all_awardings": [],
      "source": "rss"
    },
    {
      "id": "oqhsbii",
      "name": "t1_oqhsbii",
      "author": "Saltire_Blue",
      "body": "",
      "body_html": "<!-- SC_OFF --><div class=\"md\"><p>If you get the chance you should watch the documentary, it’s good </p> <p>First time in Brazil and he ends up in Cafu house having a coffee </p> <p>No bad </p> </div><!-- SC_ON -->",
      "created_utc": null,
      "created_datetime": null,
      "score": 0,
      "ups": 0,
      "downs": 0,
      "parent_id": "t3_1u0c9dc",
      "depth": 0,
      "author_flair_text": "",
      "author_flair_css_class": "",
      "author_fullname": "",
      "edited": false,
      "is_submitter": false,
      "distinguished": null,
      "stickied": false,
      "controversiality": 0,
      "total_awards_received": 0,
      "all_awardings": [],
      "source": "rss"
    },
    {
      "id": "oqjkfie",
      "name": "t1_oqjkfie",
      "author": "DoYouTrustToothpaste",
      "body": "",
      "body_html": "<!-- SC_OFF --><div class=\"md\"><p>Ends up in Cafu Café, you might say.</p> </div><!-- SC_ON -->",
      "created_utc": null,
      "created_datetime": null,
      "score": 0,
      "ups": 0,
      "downs": 0,
      "parent_id": "t3_1u0c9dc",
      "depth": 0,
      "author_flair_text": "",
      "author_flair_css_class": "",
      "author_fullname": "",
      "edited": false,
      "is_submitter": false,
      "distinguished": null,
      "stickied": false,
      "controversiality": 0,
      "total_awards_received": 0,
      "all_awardings": [],
      "source": "rss"
    },
    {
      "id": "oqh241a",
      "name": "t1_oqh241a",
      "author": "sadhill",
      "body": "",
      "body_html": "<!-- SC_OFF --><div class=\"md\"><blockquote> <p>football without fans is nothing</p> </blockquote> <p>But they call it soccer and would push their allies into the grave for a dollar </p> </div><!-- SC_ON -->",
      "created_utc": null,
      "created_datetime": null,
      "score": 0,
      "ups": 0,
      "downs": 0,
      "parent_id": "t3_1u0c9dc",
      "depth": 0,
      "author_flair_text": "",
      "author_flair_css_class": "",
      "author_fullname": "",
      "edited": false,
      "is_submitter": false,
      "distinguished": null,
      "stickied": false,
      "controversiality": 0,
      "total_awards_received": 0,
      "all_awardings": [],
      "source": "rss"
    },
    {
      "id": "oqh8vzt",
      "name": "t1_oqh8vzt",
      "author": "Prophet_Of_Helix",
      "body": "",
      "body_html": "<!-- SC_OFF --><div class=\"md\"><p>People need to realize this isn’t just about the US, this is mostly a FIFA thing.</p> <p>FIFA can never let the US host another WC ever.</p> <p>But that won’t change the corruption at the FIFA level.</p> <p>I do think with how expensive everything has gotten in the US, it doesn’t make sense to hold these international tournaments here.</p> <p>But FIFA need to make sure the same shit doesn’t happen if it’s hosted in England, or Australia, or wherever.</p> </div><!-- SC_ON -->",
      "created_utc": null,
      "created_datetime": null,
      "score": 0,
      "ups": 0,
      "downs": 0,
      "parent_id": "t3_1u0c9dc",
      "depth": 0,
      "author_flair_text": "",
      "author_flair_css_class": "",
      "author_fullname": "",
      "edited": false,
      "is_submitter": false,
      "distinguished": null,
      "stickied": false,
      "controversiality": 0,
      "total_awards_received": 0,
      "all_awardings": [],
      "source": "rss"
    },
    {
      "id": "oqhlpnf",
      "name": "t1_oqhlpnf",
      "author": "Srg11",
      "body": "",
      "body_html": "<!-- SC_OFF --><div class=\"md\"><p>It’s a perfect marriage of FIFA corruption and American capitalist corruption. They found each other at the perfect time. </p> <p>This wouldn’t happen in other countries. The pricing wouldn’t stand, and the resell markets are illegal in a lot of countries too. </p> </div><!-- SC_ON -->",
      "created_utc": null,
      "created_datetime": null,
      "score": 0,
      "ups": 0,
      "downs": 0,
      "parent_id": "t3_1u0c9dc",
      "depth": 0,
      "author_flair_text": "",
      "author_flair_css_class": "",
      "author_fullname": "",
      "edited": false,
      "is_submitter": false,
      "distinguished": null,
      "stickied": false,
      "controversiality": 0,
      "total_awards_received": 0,
      "all_awardings": [],
      "source": "rss"
    },
    {
      "id": "oqjrz35",
      "name": "t1_oqjrz35",
      "author": "congeal",
      "body": "",
      "body_html": "<!-- SC_OFF --><div class=\"md\"><blockquote> <p>But they call it soccer and would push their allies into the grave for a dollar</p> </blockquote> <p>We don't even need the dollar anymore!</p> </div><!-- SC_ON -->",
      "created_utc": null,
      "created_datetime": null,
      "score": 0,
      "ups": 0,
      "downs": 0,
      "parent_id": "t3_1u0c9dc",
      "depth": 0,
      "author_flair_text": "",
      "author_flair_css_class": "",
      "author_fullname": "",
      "edited": false,
      "is_submitter": false,
      "distinguished": null,
      "stickied": false,
      "controversiality": 0,
      "total_awards_received": 0,
      "all_awardings": [],
      "source": "rss"
    },
    {
      "id": "oqh3d0y",
      "name": "t1_oqh3d0y",
      "author": "cafesolitito",
      "body": "",
      "body_html": "<!-- SC_OFF --><div class=\"md\"><p>\"You get in there and make this about the US\" pointing at mirror meme </p> <p>Also, soccer was invited by Brits and is still used in Canada, Australia, South Africa, AND England. </p> </div><!-- SC_ON -->",
      "created_utc": null,
      "created_datetime": null,
      "score": 0,
      "ups": 0,
      "downs": 0,
      "parent_id": "t3_1u0c9dc",
      "depth": 0,
      "author_flair_text": "",
      "author_flair_css_class": "",
      "author_fullname": "",
      "edited": false,
      "is_submitter": false,
      "distinguished": null,
      "stickied": false,
      "controversiality": 0,
      "total_awards_received": 0,
      "all_awardings": [],
      "source": "rss"
    },
    {
      "id": "oqh3ixx",
      "name": "t1_oqh3ixx",
      "author": "ComaMierdaHijueputa",
      "body": "",
      "body_html": "<!-- SC_OFF --><div class=\"md\"><p>The US made it about themselves when they agreed to host it…..lmao. Not even counting the other bullshit they’ve pulled</p> </div><!-- SC_ON -->",
      "created_utc": null,
      "created_datetime": null,
      "score": 0,
      "ups": 0,
      "downs": 0,
      "parent_id": "t3_1u0c9dc",
      "depth": 0,
      "author_flair_text": "",
      "author_flair_css_class": "",
      "author_fullname": "",
      "edited": false,
      "is_submitter": false,
      "distinguished": null,
      "stickied": false,
      "controversiality": 0,
      "total_awards_received": 0,
      "all_awardings": [],
      "source": "rss"
    },
    {
      "id": "oqh3qjt",
      "name": "t1_oqh3qjt",
      "author": "cafesolitito",
      "body": "",
      "body_html": "<!-- SC_OFF --><div class=\"md\"><p>Wait, so the World Cup was affordable before 2026? Tickets were cheap before 2026? Is that what you're telling me? </p> </div><!-- SC_ON -->",
      "created_utc": null,
      "created_datetime": null,
      "score": 0,
      "ups": 0,
      "downs": 0,
      "parent_id": "t3_1u0c9dc",
      "depth": 0,
      "author_flair_text": "",
      "author_flair_css_class": "",
      "author_fullname": "",
      "edited": false,
      "is_submitter": false,
      "distinguished": null,
      "stickied": false,
      "controversiality": 0,
      "total_awards_received": 0,
      "all_awardings": [],
      "source": "rss"
    },
    {
      "id": "oqh9dyw",
      "name": "t1_oqh9dyw",
      "author": "TheRedditK9",
      "body": "",
      "body_html": "<!-- SC_OFF --><div class=\"md\"><p>The cheapest tickets for the final in 2022 were €176, the cheapest tickets for the 2026 final are €1736.</p> </div><!-- SC_ON -->",
      "created_utc": null,
      "created_datetime": null,
      "score": 0,
      "ups": 0,
      "downs": 0,
      "parent_id": "t3_1u0c9dc",
      "depth": 0,
      "author_flair_text": "",
      "author_flair_css_class": "",
      "author_fullname": "",
      "edited": false,
      "is_submitter": false,
      "distinguished": null,
      "stickied": false,
      "controversiality": 0,
      "total_awards_received": 0,
      "all_awardings": [],
      "source": "rss"
    },
    {
      "id": "oqh6pps",
      "name": "t1_oqh6pps",
      "author": "InitialSubstantial67",
      "body": "",
      "body_html": "<!-- SC_OFF --><div class=\"md\"><p>Yeah having watched the World Cup in 2022 in Qatar, it was affordable. The price have skyrocketed in this one, from accomodation, tickets, travel etc. </p> </div><!-- SC_ON -->",
      "created_utc": null,
      "created_datetime": null,
      "score": 0,
      "ups": 0,
      "downs": 0,
      "parent_id": "t3_1u0c9dc",
      "depth": 0,
      "author_flair_text": "",
      "author_flair_css_class": "",
      "author_fullname": "",
      "edited": false,
      "is_submitter": false,
      "distinguished": null,
      "stickied": false,
      "controversiality": 0,
      "total_awards_received": 0,
      "all_awardings": [],
      "source": "rss"
    },
    {
      "id": "oqh72ku",
      "name": "t1_oqh72ku",
      "author": "PalomSage",
      "body": "",
      "body_html": "<!-- SC_OFF --><div class=\"md\"><p>Yeah, they were MUCH cheaper.</p> </div><!-- SC_ON -->",
      "created_utc": null,
      "created_datetime": null,
      "score": 0,
      "ups": 0,
      "downs": 0,
      "parent_id": "t3_1u0c9dc",
      "depth": 0,
      "author_flair_text": "",
      "author_flair_css_class": "",
      "author_fullname": "",
      "edited": false,
      "is_submitter": false,
      "distinguished": null,
      "stickied": false,
      "controversiality": 0,
      "total_awards_received": 0,
      "all_awardings": [],
      "source": "rss"
    },
    {
      "id": "oqh6lvr",
      "name": "t1_oqh6lvr",
      "author": "Novrev",
      "body": "",
      "body_html": "<!-- SC_OFF --><div class=\"md\"><p>They were far cheaper, yes, <a href=\"https://www.reddit.com/r/soccer/s/vj20XKoGjl\">as seen here</a>. I don’t know if I’d go as far as affordable for all of them but certainly not the pisstake that the US and FIFA have pushed for this time around.</p> </div><!-- SC_ON -->",
      "created_utc": null,
      "created_datetime": null,
      "score": 0,
      "ups": 0,
      "downs": 0,
      "parent_id": "t3_1u0c9dc",
      "depth": 0,
      "author_flair_text": "",
      "author_flair_css_class": "",
      "author_fullname": "",
      "edited": false,
      "is_submitter": false,
      "distinguished": null,
      "stickied": false,
      "controversiality": 0,
      "total_awards_received": 0,
      "all_awardings": [],
      "source": "rss"
    },
    {
      "id": "oqh9gs0",
      "name": "t1_oqh9gs0",
      "author": "Prophet_Of_Helix",
      "body": "",
      "body_html": "<!-- SC_OFF --><div class=\"md\"><p>Important to note too this isn’t just post Covid shananagins. Yes EVERYTHING has gotten more expensive since 2021/2022, but not several orders of magnitude more expensive.</p> <p>Unfortunately these are typical prices for events in the US now.</p> <p>It probably doesn’t make sense for the US or Canada to international tourneys like this in the future.</p> </div><!-- SC_ON -->",
      "created_utc": null,
      "created_datetime": null,
      "score": 0,
      "ups": 0,
      "downs": 0,
      "parent_id": "t3_1u0c9dc",
      "depth": 0,
      "author_flair_text": "",
      "author_flair_css_class": "",
      "author_fullname": "",
      "edited": false,
      "is_submitter": false,
      "distinguished": null,
      "stickied": false,
      "controversiality": 0,
      "total_awards_received": 0,
      "all_awardings": [],
      "source": "rss"
    },
    {
      "id": "oqhaqig",
      "name": "t1_oqhaqig",
      "author": "jjw1998",
      "body": "",
      "body_html": "<!-- SC_OFF --><div class=\"md\"><p>Qatar and Russia were both incredibly easy to attend, yeah </p> </div><!-- SC_ON -->",
      "created_utc": null,
      "created_datetime": null,
      "score": 0,
      "ups": 0,
      "downs": 0,
      "parent_id": "t3_1u0c9dc",
      "depth": 0,
      "author_flair_text": "",
      "author_flair_css_class": "",
      "author_fullname": "",
      "edited": false,
      "is_submitter": false,
      "distinguished": null,
      "stickied": false,
      "controversiality": 0,
      "total_awards_received": 0,
      "all_awardings": [],
      "source": "rss"
    },
    {
      "id": "oqh4ud8",
      "name": "t1_oqh4ud8",
      "author": "ComaMierdaHijueputa",
      "body": "",
      "body_html": "<!-- SC_OFF --><div class=\"md\"><p>Do you just enjoy creating strawman arguments? Lmao </p> </div><!-- SC_ON -->",
      "created_utc": null,
      "created_datetime": null,
      "score": 0,
      "ups": 0,
      "downs": 0,
      "parent_id": "t3_1u0c9dc",
      "depth": 0,
      "author_flair_text": "",
      "author_flair_css_class": "",
      "author_fullname": "",
      "edited": false,
      "is_submitter": false,
      "distinguished": null,
      "stickied": false,
      "controversiality": 0,
      "total_awards_received": 0,
      "all_awardings": [],
      "source": "rss"
    },
    {
      "id": "oqh5jtu",
      "name": "t1_oqh5jtu",
      "author": "cafesolitito",
      "body": "",
      "body_html": "<!-- SC_OFF --><div class=\"md\"><p>No me entiendes y dejamoslo ahi </p> </div><!-- SC_ON -->",
      "created_utc": null,
      "created_datetime": null,
      "score": 0,
      "ups": 0,
      "downs": 0,
      "parent_id": "t3_1u0c9dc",
      "depth": 0,
      "author_flair_text": "",
      "author_flair_css_class": "",
      "author_fullname": "",
      "edited": false,
      "is_submitter": false,
      "distinguished": null,
      "stickied": false,
      "controversiality": 0,
      "total_awards_received": 0,
      "all_awardings": [],
      "source": "rss"
    },
    {
      "id": "oqh4js1",
      "name": "t1_oqh4js1",
      "author": "Jacobutera",
      "body": "",
      "body_html": "<!-- SC_OFF --><div class=\"md\"><p>Uneducated comment </p> </div><!-- SC_ON -->",
      "created_utc": null,
      "created_datetime": null,
      "score": 0,
      "ups": 0,
      "downs": 0,
      "parent_id": "t3_1u0c9dc",
      "depth": 0,
      "author_flair_text": "",
      "author_flair_css_class": "",
      "author_fullname": "",
      "edited": false,
      "is_submitter": false,
      "distinguished": null,
      "stickied": false,
      "controversiality": 0,
      "total_awards_received": 0,
      "all_awardings": [],
      "source": "rss"
    },
    {
      "id": "oqh5r9z",
      "name": "t1_oqh5r9z",
      "author": "C0mm0nVillain",
      "body": "",
      "body_html": "<!-- SC_OFF --><div class=\"md\"><p>\"Ye its sad\" is what i hear a lot from players. Maybe players can protest for us to make this change....</p> </div><!-- SC_ON -->",
      "created_utc": null,
      "created_datetime": null,
      "score": 0,
      "ups": 0,
      "downs": 0,
      "parent_id": "t3_1u0c9dc",
      "depth": 0,
      "author_flair_text": "",
      "author_flair_css_class": "",
      "author_fullname": "",
      "edited": false,
      "is_submitter": false,
      "distinguished": null,
      "stickied": false,
      "controversiality": 0,
      "total_awards_received": 0,
      "all_awardings": [],
      "source": "rss"
    },
    {
      "id": "oqh70kd",
      "name": "t1_oqh70kd",
      "author": "outrageousVoid07",
      "body": "",
      "body_html": "<!-- SC_OFF --><div class=\"md\"><p>There's an argument that it's our responsibility to bring about than change as the people who get the bad end of the stick, however, I do not see how players protesting would change anything unless they are asking for a mass boycott from fans</p> </div><!-- SC_ON -->",
      "created_utc": null,
      "created_datetime": null,
      "score": 0,
      "ups": 0,
      "downs": 0,
      "parent_id": "t3_1u0c9dc",
      "depth": 0,
      "author_flair_text": "",
      "author_flair_css_class": "",
      "author_fullname": "",
      "edited": false,
      "is_submitter": false,
      "distinguished": null,
      "stickied": false,
      "controversiality": 0,
      "total_awards_received": 0,
      "all_awardings": [],
      "source": "rss"
    },
    {
      "id": "oqhcg24",
      "name": "t1_oqhcg24",
      "author": "gotfcgo",
      "body": "",
      "body_html": "<!-- SC_OFF --><div class=\"md\"><p>Welcome to North America, sport is for the affluent.</p> </div><!-- SC_ON -->",
      "created_utc": null,
      "created_datetime": null,
      "score": 0,
      "ups": 0,
      "downs": 0,
      "parent_id": "t3_1u0c9dc",
      "depth": 0,
      "author_flair_text": "",
      "author_flair_css_class": "",
      "author_fullname": "",
      "edited": false,
      "is_submitter": false,
      "distinguished": null,
      "stickied": false,
      "controversiality": 0,
      "total_awards_received": 0,
      "all_awardings": [],
      "source": "rss"
    },
    {
      "id": "oqjsnqs",
      "name": "t1_oqjsnqs",
      "author": "congeal",
      "body": "",
      "body_html": "<!-- SC_OFF --><div class=\"md\"><p>the affluent effluence</p> </div><!-- SC_ON -->",
      "created_utc": null,
      "created_datetime": null,
      "score": 0,
      "ups": 0,
      "downs": 0,
      "parent_id": "t3_1u0c9dc",
      "depth": 0,
      "author_flair_text": "",
      "author_flair_css_class": "",
      "author_fullname": "",
      "edited": false,
      "is_submitter": false,
      "distinguished": null,
      "stickied": false,
      "controversiality": 0,
      "total_awards_received": 0,
      "all_awardings": [],
      "source": "rss"
    },
    {
      "id": "oqhl8kn",
      "name": "t1_oqhl8kn",
      "author": "voi_bet",
      "body": "",
      "body_html": "<!-- SC_OFF --><div class=\"md\"><p>This is the part FIFA never seems to understand: the travelling supporters are part of the product. Price them out and you don't get a premium event, you get a TV studio with nicer grass.</p> </div><!-- SC_ON -->",
      "created_utc": null,
      "created_datetime": null,
      "score": 0,
      "ups": 0,
      "downs": 0,
      "parent_id": "t3_1u0c9dc",
      "depth": 0,
      "author_flair_text": "",
      "author_flair_css_class": "",
      "author_fullname": "",
      "edited": false,
      "is_submitter": false,
      "distinguished": null,
      "stickied": false,
      "controversiality": 0,
      "total_awards_received": 0,
      "all_awardings": [],
      "source": "rss"
    },
    {
      "id": "oqhsrnj",
      "name": "t1_oqhsrnj",
      "author": "FailFastandDieYoung",
      "body": "",
      "body_html": "<!-- SC_OFF --><div class=\"md\"><p>The US: “give me 1,000 quid, or you’re getting stabbed”</p> </div><!-- SC_ON -->",
      "created_utc": null,
      "created_datetime": null,
      "score": 0,
      "ups": 0,
      "downs": 0,
      "parent_id": "t3_1u0c9dc",
      "depth": 0,
      "author_flair_text": "",
      "author_flair_css_class": "",
      "author_fullname": "",
      "edited": false,
      "is_submitter": false,
      "distinguished": null,
      "stickied": false,
      "controversiality": 0,
      "total_awards_received": 0,
      "all_awardings": [],
      "source": "rss"
    },
    {
      "id": "oqjccjl",
      "name": "t1_oqjccjl",
      "author": "SlickWilly49",
      "body": "",
      "body_html": "<!-- SC_OFF --><div class=\"md\"><p>“A 1,000 quid to not get stabbed? That’s a pretty good deal”</p> </div><!-- SC_ON -->",
      "created_utc": null,
      "created_datetime": null,
      "score": 0,
      "ups": 0,
      "downs": 0,
      "parent_id": "t3_1u0c9dc",
      "depth": 0,
      "author_flair_text": "",
      "author_flair_css_class": "",
      "author_fullname": "",
      "edited": false,
      "is_submitter": false,
      "distinguished": null,
      "stickied": false,
      "controversiality": 0,
      "total_awards_received": 0,
      "all_awardings": [],
      "source": "rss"
    },
    {
      "id": "oqjvqyo",
      "name": "t1_oqjvqyo",
      "author": "FailFastandDieYoung",
      "body": "",
      "body_html": "<!-- SC_OFF --><div class=\"md\"><p>In this financial climate!</p> </div><!-- SC_ON -->",
      "created_utc": null,
      "created_datetime": null,
      "score": 0,
      "ups": 0,
      "downs": 0,
      "parent_id": "t3_1u0c9dc",
      "depth": 0,
      "author_flair_text": "",
      "author_flair_css_class": "",
      "author_fullname": "",
      "edited": false,
      "is_submitter": false,
      "distinguished": null,
      "stickied": false,
      "controversiality": 0,
      "total_awards_received": 0,
      "all_awardings": [],
      "source": "rss"
    },
    {
      "id": "oqjsu8y",
      "name": "t1_oqjsu8y",
      "author": "congeal",
      "body": "",
      "body_html": "<!-- SC_OFF --><div class=\"md\"><p>guns don't stab very well</p> </div><!-- SC_ON -->",
      "created_utc": null,
      "created_datetime": null,
      "score": 0,
      "ups": 0,
      "downs": 0,
      "parent_id": "t3_1u0c9dc",
      "depth": 0,
      "author_flair_text": "",
      "author_flair_css_class": "",
      "author_fullname": "",
      "edited": false,
      "is_submitter": false,
      "distinguished": null,
      "stickied": false,
      "controversiality": 0,
      "total_awards_received": 0,
      "all_awardings": [],
      "source": "rss"
    },
    {
      "id": "oqhhelc",
      "name": "t1_oqhhelc",
      "author": "Ill_Ad_791",
      "body": "",
      "body_html": "<!-- SC_OFF --><div class=\"md\"><p>I’ve always thought these guys look similar and are also from the same town..</p> </div><!-- SC_ON -->",
      "created_utc": null,
      "created_datetime": null,
      "score": 0,
      "ups": 0,
      "downs": 0,
      "parent_id": "t3_1u0c9dc",
      "depth": 0,
      "author_flair_text": "",
      "author_flair_css_class": "",
      "author_fullname": "",
      "edited": false,
      "is_submitter": false,
      "distinguished": null,
      "stickied": false,
      "controversiality": 0,
      "total_awards_received": 0,
      "all_awardings": [],
      "source": "rss"
    },
    {
      "id": "oqhhrif",
      "name": "t1_oqhhrif",
      "author": "JaffaCakeJunkie",
      "body": "",
      "body_html": "<!-- SC_OFF --><div class=\"md\"><p>It mainly highlights the cultural difference between North America and Europe's attitude towards events. I moved to Canada almost 20years ago from northern England and the biggest culture shock when I got here was event ticket pricing, concerts, stand-up, etc. And FIFA jumped in both feet when they knew they could make a lot of money. </p> <p>FIFA should have done a lot differently here but ultimately they don't care about anything but money, that's been clear for a long time. </p> </div><!-- SC_ON -->",
      "created_utc": null,
      "created_datetime": null,
      "score": 0,
      "ups": 0,
      "downs": 0,
      "parent_id": "t3_1u0c9dc",
      "depth": 0,
      "author_flair_text": "",
      "author_flair_css_class": "",
      "author_fullname": "",
      "edited": false,
      "is_submitter": false,
      "distinguished": null,
      "stickied": false,
      "controversiality": 0,
      "total_awards_received": 0,
      "all_awardings": [],
      "source": "rss"
    },
    {
      "id": "oqhx2ao",
      "name": "t1_oqhx2ao",
      "author": "JonnyReece",
      "body": "",
      "body_html": "<!-- SC_OFF --><div class=\"md\"><p>That's my Captain. Go well SJM.</p> <p>UTV! </p> </div><!-- SC_ON -->",
      "created_utc": null,
      "created_datetime": null,
      "score": 0,
      "ups": 0,
      "downs": 0,
      "parent_id": "t3_1u0c9dc",
      "depth": 0,
      "author_flair_text": "",
      "author_flair_css_class": "",
      "author_fullname": "",
      "edited": false,
      "is_submitter": false,
      "distinguished": null,
      "stickied": false,
      "controversiality": 0,
      "total_awards_received": 0,
      "all_awardings": [],
      "source": "rss"
    },
    {
      "id": "oqjch47",
      "name": "t1_oqjch47",
      "author": "Okey114",
      "body": "",
      "body_html": "<!-- SC_OFF --><div class=\"md\"><p>We're calling it \"The expensive game\" now boys. </p> </div><!-- SC_ON -->",
      "created_utc": null,
      "created_datetime": null,
      "score": 0,
      "ups": 0,
      "downs": 0,
      "parent_id": "t3_1u0c9dc",
      "depth": 0,
      "author_flair_text": "",
      "author_flair_css_class": "",
      "author_fullname": "",
      "edited": false,
      "is_submitter": false,
      "distinguished": null,
      "stickied": false,
      "controversiality": 0,
      "total_awards_received": 0,
      "all_awardings": [],
      "source": "rss"
    },
    {
      "id": "oqh3065",
      "name": "t1_oqh3065",
      "author": "Emergency-Mobile8612",
      "body": "",
      "body_html": "<!-- SC_OFF --><div class=\"md\"><p>What FIFA does is more than sad, sad is people whose life is their country’s national football team.</p> <p>What FIFA does is exploitative, greedy, and inconsiderate.</p> </div><!-- SC_ON -->",
      "created_utc": null,
      "created_datetime": null,
      "score": 0,
      "ups": 0,
      "downs": 0,
      "parent_id": "t3_1u0c9dc",
      "depth": 0,
      "author_flair_text": "",
      "author_flair_css_class": "",
      "author_fullname": "",
      "edited": false,
      "is_submitter": false,
      "distinguished": null,
      "stickied": false,
      "controversiality": 0,
      "total_awards_received": 0,
      "all_awardings": [],
      "source": "rss"
    },
    {
      "id": "oqh4u7u",
      "name": "t1_oqh4u7u",
      "author": "Outside-Leopard-9783",
      "body": "",
      "body_html": "<!-- SC_OFF --><div class=\"md\"><p>Life can be hard for people, having a passion can make it a lot easier. Dont think it should be called sad though </p> </div><!-- SC_ON -->",
      "created_utc": null,
      "created_datetime": null,
      "score": 0,
      "ups": 0,
      "downs": 0,
      "parent_id": "t3_1u0c9dc",
      "depth": 0,
      "author_flair_text": "",
      "author_flair_css_class": "",
      "author_fullname": "",
      "edited": false,
      "is_submitter": false,
      "distinguished": null,
      "stickied": false,
      "controversiality": 0,
      "total_awards_received": 0,
      "all_awardings": [],
      "source": "rss"
    },
    {
      "id": "oqh5d44",
      "name": "t1_oqh5d44",
      "author": "Emergency-Mobile8612",
      "body": "",
      "body_html": "<!-- SC_OFF --><div class=\"md\"><p>Right, I get why it happens, and I’m not necessarily blaming those people.</p> <p>But if not sad, what would you call it?</p> </div><!-- SC_ON -->",
      "created_utc": null,
      "created_datetime": null,
      "score": 0,
      "ups": 0,
      "downs": 0,
      "parent_id": "t3_1u0c9dc",
      "depth": 0,
      "author_flair_text": "",
      "author_flair_css_class": "",
      "author_fullname": "",
      "edited": false,
      "is_submitter": false,
      "distinguished": null,
      "stickied": false,
      "controversiality": 0,
      "total_awards_received": 0,
      "all_awardings": [],
      "source": "rss"
    },
    {
      "id": "oqh7avq",
      "name": "t1_oqh7avq",
      "author": "no1kopite",
      "body": "",
      "body_html": "<!-- SC_OFF --><div class=\"md\"><p>A passionate hobby. Just as pointless as most. </p> </div><!-- SC_ON -->",
      "created_utc": null,
      "created_datetime": null,
      "score": 0,
      "ups": 0,
      "downs": 0,
      "parent_id": "t3_1u0c9dc",
      "depth": 0,
      "author_flair_text": "",
      "author_flair_css_class": "",
      "author_fullname": "",
      "edited": false,
      "is_submitter": false,
      "distinguished": null,
      "stickied": false,
      "controversiality": 0,
      "total_awards_received": 0,
      "all_awardings": [],
      "source": "rss"
    },
    {
      "id": "oqhn2pz",
      "name": "t1_oqhn2pz",
      "author": "Emergency-Mobile8612",
      "body": "",
      "body_html": "<!-- SC_OFF --><div class=\"md\"><p>I disagree, many hobbies are about producing while others are about consuming. I tend to believe hobbies where people produce/create whatever it is are more fulfilling.</p> <p>But I do get where you guys are coming from, it makes sense to see it like that.</p> </div><!-- SC_ON -->",
      "created_utc": null,
      "created_datetime": null,
      "score": 0,
      "ups": 0,
      "downs": 0,
      "parent_id": "t3_1u0c9dc",
      "depth": 0,
      "author_flair_text": "",
      "author_flair_css_class": "",
      "author_fullname": "",
      "edited": false,
      "is_submitter": false,
      "distinguished": null,
      "stickied": false,
      "controversiality": 0,
      "total_awards_received": 0,
      "all_awardings": [],
      "source": "rss"
    },
    {
      "id": "oqh7lty",
      "name": "t1_oqh7lty",
      "author": "hits_riders_soak",
      "body": "",
      "body_html": "<!-- SC_OFF --><div class=\"md\"><p>commited. passionate. </p> <p>for many it is life expanding, full of friends, community, travel and positive experiences. </p> <p>that doesn't sound sad to me. </p> </div><!-- SC_ON -->",
      "created_utc": null,
      "created_datetime": null,
      "score": 0,
      "ups": 0,
      "downs": 0,
      "parent_id": "t3_1u0c9dc",
      "depth": 0,
      "author_flair_text": "",
      "author_flair_css_class": "",
      "author_fullname": "",
      "edited": false,
      "is_submitter": false,
      "distinguished": null,
      "stickied": false,
      "controversiality": 0,
      "total_awards_received": 0,
      "all_awardings": [],
      "source": "rss"
    },
    {
      "id": "oqhagys",
      "name": "t1_oqhagys",
      "author": "xiovelrach",
      "body": "",
      "body_html": "<!-- SC_OFF --><div class=\"md\"><p>Was just in LA this weekend, stayed at what used to be one of my favorite hotels in Culver City. The hotel now has a deal with something called \"Resort Pass\" where anyone can reserve pool sections via their website (non-hotel guests included), which put a pretty big cloud over an otherwise great weekend. The worst part was how poorly the hotel and their staff handled the whole situation.</p> <p>Not sure if other countries have done things like this yet, but the enshitification of pretty much anything that used to be good is really draining on me. I can't see why anyone wanting to come here and be nickle and dimed for everything, and then paying $1K+ per ticket to see a game.</p> </div><!-- SC_ON -->",
      "created_utc": null,
      "created_datetime": null,
      "score": 0,
      "ups": 0,
      "downs": 0,
      "parent_id": "t3_1u0c9dc",
      "depth": 0,
      "author_flair_text": "",
      "author_flair_css_class": "",
      "author_fullname": "",
      "edited": false,
      "is_submitter": false,
      "distinguished": null,
      "stickied": false,
      "controversiality": 0,
      "total_awards_received": 0,
      "all_awardings": [],
      "source": "rss"
    },
    {
      "id": "oqjskkr",
      "name": "t1_oqjskkr",
      "author": "congeal",
      "body": "",
      "body_html": "<!-- SC_OFF --><div class=\"md\"><p>reserve pool sections? Are they reserving areas around the pool for certain amounts of time each day? That's weird and I can imagine it causes all kinds of problems.</p> </div><!-- SC_ON -->",
      "created_utc": null,
      "created_datetime": null,
      "score": 0,
      "ups": 0,
      "downs": 0,
      "parent_id": "t3_1u0c9dc",
      "depth": 0,
      "author_flair_text": "",
      "author_flair_css_class": "",
      "author_fullname": "",
      "edited": false,
      "is_submitter": false,
      "distinguished": null,
      "stickied": false,
      "controversiality": 0,
      "total_awards_received": 0,
      "all_awardings": [],
      "source": "rss"
    },
    {
      "id": "oqjvn2t",
      "name": "t1_oqjvn2t",
      "author": "xiovelrach",
      "body": "",
      "body_html": "<!-- SC_OFF --><div class=\"md\"><p>Yes and you don't automatically get them for being guests at the pool. So if they're all \"reserved\", guests are fucked lol </p> </div><!-- SC_ON -->",
      "created_utc": null,
      "created_datetime": null,
      "score": 0,
      "ups": 0,
      "downs": 0,
      "parent_id": "t3_1u0c9dc",
      "depth": 0,
      "author_flair_text": "",
      "author_flair_css_class": "",
      "author_fullname": "",
      "edited": false,
      "is_submitter": false,
      "distinguished": null,
      "stickied": false,
      "controversiality": 0,
      "total_awards_received": 0,
      "all_awardings": [],
      "source": "rss"
    },
    {
      "id": "oqjwjsp",
      "name": "t1_oqjwjsp",
      "author": "congeal",
      "body": "",
      "body_html": "<!-- SC_OFF --><div class=\"md\"><p>wow</p> <p>try telling kids they can't play in the pool at the hotel...</p> <p>hey kids, just jump in the bathtub, oh, the bathtub rooms are extra</p> </div><!-- SC_ON -->",
      "created_utc": null,
      "created_datetime": null,
      "score": 0,
      "ups": 0,
      "downs": 0,
      "parent_id": "t3_1u0c9dc",
      "depth": 0,
      "author_flair_text": "",
      "author_flair_css_class": "",
      "author_fullname": "",
      "edited": false,
      "is_submitter": false,
      "distinguished": null,
      "stickied": false,
      "controversiality": 0,
      "total_awards_received": 0,
      "all_awardings": [],
      "source": "rss"
    },
    {
      "id": "oqqqt9w",
      "name": "t1_oqqqt9w",
      "author": "pahweee",
      "body": "",
      "body_html": "<!-- SC_OFF --><div class=\"md\"><p>And also, football without Origi is nothing </p> </div><!-- SC_ON -->",
      "created_utc": null,
      "created_datetime": null,
      "score": 0,
      "ups": 0,
      "downs": 0,
      "parent_id": "t3_1u0c9dc",
      "depth": 0,
      "author_flair_text": "",
      "author_flair_css_class": "",
      "author_fullname": "",
      "edited": false,
      "is_submitter": false,
      "distinguished": null,
      "stickied": false,
      "controversiality": 0,
      "total_awards_received": 0,
      "all_awardings": [],
      "source": "rss"
    },
    {
      "id": "oqt1r07",
      "name": "t1_oqt1r07",
      "author": "nenadsuperzmaj",
      "body": "",
      "body_html": "<!-- SC_OFF --><div class=\"md\"><p>Just you thread carefully, pal.</p> </div><!-- SC_ON -->",
      "created_utc": null,
      "created_datetime": null,
      "score": 0,
      "ups": 0,
      "downs": 0,
      "parent_id": "t3_1u0c9dc",
      "depth": 0,
      "author_flair_text": "",
      "author_flair_css_class": "",
      "author_fullname": "",
      "edited": false,
      "is_submitter": false,
      "distinguished": null,
      "stickied": false,
      "controversiality": 0,
      "total_awards_received": 0,
      "all_awardings": [],
      "source": "rss"
    },
    {
      "id": "oqh8961",
      "name": "t1_oqh8961",
      "author": "generalissimo1",
      "body": "",
      "body_html": "<!-- SC_OFF --><div class=\"md\"><p>Football without fans is just as sad as football without Origi 😞</p> </div><!-- SC_ON -->",
      "created_utc": null,
      "created_datetime": null,
      "score": 0,
      "ups": 0,
      "downs": 0,
      "parent_id": "t3_1u0c9dc",
      "depth": 0,
      "author_flair_text": "",
      "author_flair_css_class": "",
      "author_fullname": "",
      "edited": false,
      "is_submitter": false,
      "distinguished": null,
      "stickied": false,
      "controversiality": 0,
      "total_awards_received": 0,
      "all_awardings": [],
      "source": "rss"
    },
    {
      "id": "oqhicwa",
      "name": "t1_oqhicwa",
      "author": "WaveDave1988",
      "body": "",
      "body_html": "<!-- SC_OFF --><div class=\"md\"><p>Is there any video of this with subtitles? Dont understand any of it. I cannae help it</p> </div><!-- SC_ON -->",
      "created_utc": null,
      "created_datetime": null,
      "score": 0,
      "ups": 0,
      "downs": 0,
      "parent_id": "t3_1u0c9dc",
      "depth": 0,
      "author_flair_text": "",
      "author_flair_css_class": "",
      "author_fullname": "",
      "edited": false,
      "is_submitter": false,
      "distinguished": null,
      "stickied": false,
      "controversiality": 0,
      "total_awards_received": 0,
      "all_awardings": [],
      "source": "rss"
    },
    {
      "id": "oqhchm9",
      "name": "t1_oqhchm9",
      "author": "SituationKey8985",
      "body": "",
      "body_html": "<!-- SC_OFF --><div class=\"md\"><p>I’m mostly out of the loop on this. What could be done to bring down the ticket prices? The insane prices are all on the re-sale market which is pure supply and demand. I suppose they could cap prices but then it just becomes a lottery of whoever can snap up the the tickets faster, like when big concert tickets go on-sale.</p> </div><!-- SC_ON -->",
      "created_utc": null,
      "created_datetime": null,
      "score": 0,
      "ups": 0,
      "downs": 0,
      "parent_id": "t3_1u0c9dc",
      "depth": 0,
      "author_flair_text": "",
      "author_flair_css_class": "",
      "author_fullname": "",
      "edited": false,
      "is_submitter": false,
      "distinguished": null,
      "stickied": false,
      "controversiality": 0,
      "total_awards_received": 0,
      "all_awardings": [],
      "source": "rss"
    },
    {
      "id": "oqhppy8",
      "name": "t1_oqhppy8",
      "author": "AfterDinnerSpeaker",
      "body": "",
      "body_html": "<!-- SC_OFF --><div class=\"md\"><p>I imagine the insane resell tickets have nothing to do with FIFA taking 15% off the buyer and 15% off the seller.</p> <p>Also, a bit fucking scammy of them to sell all those Right to Buy tokens, before they'd even announced the ticket prices.</p> </div><!-- SC_ON -->",
      "created_utc": null,
      "created_datetime": null,
      "score": 0,
      "ups": 0,
      "downs": 0,
      "parent_id": "t3_1u0c9dc",
      "depth": 0,
      "author_flair_text": "",
      "author_flair_css_class": "",
      "author_fullname": "",
      "edited": false,
      "is_submitter": false,
      "distinguished": null,
      "stickied": false,
      "controversiality": 0,
      "total_awards_received": 0,
      "all_awardings": [],
      "source": "rss"
    },
    {
      "id": "oqheswl",
      "name": "t1_oqheswl",
      "author": "GoldenDom3r",
      "body": "",
      "body_html": "<!-- SC_OFF --><div class=\"md\"><p>Also I love how are all these arguments assume that those who can afford the tickets aren’t actual fans. </p> </div><!-- SC_ON -->",
      "created_utc": null,
      "created_datetime": null,
      "score": 0,
      "ups": 0,
      "downs": 0,
      "parent_id": "t3_1u0c9dc",
      "depth": 0,
      "author_flair_text": "",
      "author_flair_css_class": "",
      "author_fullname": "",
      "edited": false,
      "is_submitter": false,
      "distinguished": null,
      "stickied": false,
      "controversiality": 0,
      "total_awards_received": 0,
      "all_awardings": [],
      "source": "rss"
    },
    {
      "id": "oqiy0uv",
      "name": "t1_oqiy0uv",
      "author": "nuedd",
      "body": "",
      "body_html": "<!-- SC_OFF --><div class=\"md\"><p>If national football is \"your life\", you need to \"get a life\".</p> </div><!-- SC_ON -->",
      "created_utc": null,
      "created_datetime": null,
      "score": 0,
      "ups": 0,
      "downs": 0,
      "parent_id": "t3_1u0c9dc",
      "depth": 0,
      "author_flair_text": "",
      "author_flair_css_class": "",
      "author_fullname": "",
      "edited": false,
      "is_submitter": false,
      "distinguished": null,
      "stickied": false,
      "controversiality": 0,
      "total_awards_received": 0,
      "all_awardings": [],
      "source": "rss"
    },
    {
      "id": "oqh9k1s",
      "name": "t1_oqh9k1s",
      "author": "manbeqrpig",
      "body": "",
      "body_html": "<!-- SC_OFF --><div class=\"md\"><p>Everything is priced fairly considering the crazy demand for this tournament. We’re seeing prices for some games rising right now. The same fans the McGinn is saying can’t come wouldn’t have been able to come anyway if tickets were initially sold at $80 a pop with a cap on resale prices because they wouldn’t have been able to get their hands on them with how many casual Americans would have been trying to buy just to say they went to a WC match. The stadium’s will be full and the atmosphere will be poor by Euro standards because it always was going to be poor being held in the US</p> </div><!-- SC_ON -->",
      "created_utc": null,
      "created_datetime": null,
      "score": 0,
      "ups": 0,
      "downs": 0,
      "parent_id": "t3_1u0c9dc",
      "depth": 0,
      "author_flair_text": "",
      "author_flair_css_class": "",
      "author_fullname": "",
      "edited": false,
      "is_submitter": false,
      "distinguished": null,
      "stickied": false,
      "controversiality": 0,
      "total_awards_received": 0,
      "all_awardings": [],
      "source": "rss"
    },
    {
      "id": "oqhrmx8",
      "name": "t1_oqhrmx8",
      "author": "offerfoxache",
      "body": "",
      "body_html": "<!-- SC_OFF --><div class=\"md\"><blockquote> <p>just to say they went to a WC match.</p> </blockquote> <p>And that's part of the problem, they're not fans, they're just going to spend the game on their phone.</p> </div><!-- SC_ON -->",
      "created_utc": null,
      "created_datetime": null,
      "score": 0,
      "ups": 0,
      "downs": 0,
      "parent_id": "t3_1u0c9dc",
      "depth": 0,
      "author_flair_text": "",
      "author_flair_css_class": "",
      "author_fullname": "",
      "edited": false,
      "is_submitter": false,
      "distinguished": null,
      "stickied": false,
      "controversiality": 0,
      "total_awards_received": 0,
      "all_awardings": [],
      "source": "rss"
    },
    {
      "id": "oqhttcv",
      "name": "t1_oqhttcv",
      "author": "manbeqrpig",
      "body": "",
      "body_html": "<!-- SC_OFF --><div class=\"md\"><p>Some fantastic gate keeping there. Am I not a fan because I wanted to go to a World Cup match and got lucky getting Scotland Haiti tickets? I’m a fan of the sport but not Scotland or Haiti so am I ruining this World Cup because I got tickets where I can easily attend instead of for the team I support? </p> </div><!-- SC_ON -->",
      "created_utc": null,
      "created_datetime": null,
      "score": 0,
      "ups": 0,
      "downs": 0,
      "parent_id": "t3_1u0c9dc",
      "depth": 0,
      "author_flair_text": "",
      "author_flair_css_class": "",
      "author_fullname": "",
      "edited": false,
      "is_submitter": false,
      "distinguished": null,
      "stickied": false,
      "controversiality": 0,
      "total_awards_received": 0,
      "all_awardings": [],
      "source": "rss"
    },
    {
      "id": "oqi7tsc",
      "name": "t1_oqi7tsc",
      "author": "offerfoxache",
      "body": "",
      "body_html": "<!-- SC_OFF --><div class=\"md\"><p>There are many Scotland fans that wanted to go having witnessed home and away games over the years, and didn't get the tickets, myself included. If you're a fan of football, then that's fine, you enjoy the game! I hope you enjoy the terrorball of Steve Clarke's football.</p> </div><!-- SC_ON -->",
      "created_utc": null,
      "created_datetime": null,
      "score": 0,
      "ups": 0,
      "downs": 0,
      "parent_id": "t3_1u0c9dc",
      "depth": 0,
      "author_flair_text": "",
      "author_flair_css_class": "",
      "author_fullname": "",
      "edited": false,
      "is_submitter": false,
      "distinguished": null,
      "stickied": false,
      "controversiality": 0,
      "total_awards_received": 0,
      "all_awardings": [],
      "source": "rss"
    },
    {
      "id": "oqhczui",
      "name": "t1_oqhczui",
      "author": "Sh0uldSign0ff",
      "body": "",
      "body_html": "<!-- SC_OFF --><div class=\"md\"><p>Are the games not going to be sold out with fans? I know fifa is pricing out middle class, but let’s not act like there won’t be fans in the stadium</p> </div><!-- SC_ON -->",
      "created_utc": null,
      "created_datetime": null,
      "score": 0,
      "ups": 0,
      "downs": 0,
      "parent_id": "t3_1u0c9dc",
      "depth": 0,
      "author_flair_text": "",
      "author_flair_css_class": "",
      "author_fullname": "",
      "edited": false,
      "is_submitter": false,
      "distinguished": null,
      "stickied": false,
      "controversiality": 0,
      "total_awards_received": 0,
      "all_awardings": [],
      "source": "rss"
    },
    {
      "id": "oqhgem6",
      "name": "t1_oqhgem6",
      "author": "AaddeMos",
      "body": "",
      "body_html": "<!-- SC_OFF --><div class=\"md\"><p>That’s why in every stadium all the chants, tifo’s and die hard fans are in the business seats. That section goes wild every match!</p> </div><!-- SC_ON -->",
      "created_utc": null,
      "created_datetime": null,
      "score": 0,
      "ups": 0,
      "downs": 0,
      "parent_id": "t3_1u0c9dc",
      "depth": 0,
      "author_flair_text": "",
      "author_flair_css_class": "",
      "author_fullname": "",
      "edited": false,
      "is_submitter": false,
      "distinguished": null,
      "stickied": false,
      "controversiality": 0,
      "total_awards_received": 0,
      "all_awardings": [],
      "source": "rss"
    },
    {
      "id": "oqhh24c",
      "name": "t1_oqhh24c",
      "author": "Sh0uldSign0ff",
      "body": "",
      "body_html": "<!-- SC_OFF --><div class=\"md\"><p>Different type of fans, but you can continue to gatekeep</p> </div><!-- SC_ON -->",
      "created_utc": null,
      "created_datetime": null,
      "score": 0,
      "ups": 0,
      "downs": 0,
      "parent_id": "t3_1u0c9dc",
      "depth": 0,
      "author_flair_text": "",
      "author_flair_css_class": "",
      "author_fullname": "",
      "edited": false,
      "is_submitter": false,
      "distinguished": null,
      "stickied": false,
      "controversiality": 0,
      "total_awards_received": 0,
      "all_awardings": [],
      "source": "rss"
    },
    {
      "id": "oqhnu6u",
      "name": "t1_oqhnu6u",
      "author": "AaddeMos",
      "body": "",
      "body_html": "<!-- SC_OFF --><div class=\"md\"><p>Without looking at your profile, I just know you are American</p> </div><!-- SC_ON -->",
      "created_utc": null,
      "created_datetime": null,
      "score": 0,
      "ups": 0,
      "downs": 0,
      "parent_id": "t3_1u0c9dc",
      "depth": 0,
      "author_flair_text": "",
      "author_flair_css_class": "",
      "author_fullname": "",
      "edited": false,
      "is_submitter": false,
      "distinguished": null,
      "stickied": false,
      "controversiality": 0,
      "total_awards_received": 0,
      "all_awardings": [],
      "source": "rss"
    },
    {
      "id": "oqi4b26",
      "name": "t1_oqi4b26",
      "author": "Sh0uldSign0ff",
      "body": "",
      "body_html": "<!-- SC_OFF --><div class=\"md\"><p>I think what people don’t realize when they look at ticket prices, is Americans would have to pay more to watch the World Cup abroad with travel. So obviously they’re willing to pay more when it’s in our country because it’s a net value. Believe it or not, there are a ton of soccer fans in the USA. It’s unfortunate that not everyone that wants to attend can, but without a real solution what would you expect</p> </div><!-- SC_ON -->",
      "created_utc": null,
      "created_datetime": null,
      "score": 0,
      "ups": 0,
      "downs": 0,
      "parent_id": "t3_1u0c9dc",
      "depth": 0,
      "author_flair_text": "",
      "author_flair_css_class": "",
      "author_fullname": "",
      "edited": false,
      "is_submitter": false,
      "distinguished": null,
      "stickied": false,
      "controversiality": 0,
      "total_awards_received": 0,
      "all_awardings": [],
      "source": "rss"
    },
    {
      "id": "oqjmlfj",
      "name": "t1_oqjmlfj",
      "author": "DoYouTrustToothpaste",
      "body": "",
      "body_html": "<!-- SC_OFF --><div class=\"md\"><p>When looking at ticket prices, we can't just compare them to NA's standards (or at least CANUSA, don't know about MEX), we have to compare them to the standard of other WCs. I don't really care that Americans don't find these prices offensive because they're in line with what they would pay for local sports, because the WC is an international tournament. This WC is already the most expensive for visitors, because the USA are the richest country on the planet, therefore everything about the trip will be expensive from the perspective of non-Americans. Well, that and the obvious price gouging taking place.</p> <p>It's nice that it's affordable for US fans, it should be, the tournament is in their country, after all. It's not nice that it's so harsh for everyone else. And you might think I'm talking about fans from poor countries, but this is true for European fans as well.</p> </div><!-- SC_ON -->",
      "created_utc": null,
      "created_datetime": null,
      "score": 0,
      "ups": 0,
      "downs": 0,
      "parent_id": "t3_1u0c9dc",
      "depth": 0,
      "author_flair_text": "",
      "author_flair_css_class": "",
      "author_fullname": "",
      "edited": false,
      "is_submitter": false,
      "distinguished": null,
      "stickied": false,
      "controversiality": 0,
      "total_awards_received": 0,
      "all_awardings": [],
      "source": "rss"
    },
    {
      "id": "oqk027f",
      "name": "t1_oqk027f",
      "author": "Sh0uldSign0ff",
      "body": "",
      "body_html": "<!-- SC_OFF --><div class=\"md\"><p>Right so Europeans are having to deal with the same thing Americans have to do with the WC is in Europe. It sucks, but really what is the alternative? I hear a lot of people calling out the problem, but no real solution</p> </div><!-- SC_ON -->",
      "created_utc": null,
      "created_datetime": null,
      "score": 0,
      "ups": 0,
      "downs": 0,
      "parent_id": "t3_1u0c9dc",
      "depth": 0,
      "author_flair_text": "",
      "author_flair_css_class": "",
      "author_fullname": "",
      "edited": false,
      "is_submitter": false,
      "distinguished": null,
      "stickied": false,
      "controversiality": 0,
      "total_awards_received": 0,
      "all_awardings": [],
      "source": "rss"
    },
    {
      "id": "oqn5fdk",
      "name": "t1_oqn5fdk",
      "author": "GetItUpYee",
      "body": "",
      "body_html": "<!-- SC_OFF --><div class=\"md\"><p>Wrong. Ticket prices in European WCs have been drastically lower. As have domestic travel costs when in host country.</p> </div><!-- SC_ON -->",
      "created_utc": null,
      "created_datetime": null,
      "score": 0,
      "ups": 0,
      "downs": 0,
      "parent_id": "t3_1u0c9dc",
      "depth": 0,
      "author_flair_text": "",
      "author_flair_css_class": "",
      "author_fullname": "",
      "edited": false,
      "is_submitter": false,
      "distinguished": null,
      "stickied": false,
      "controversiality": 0,
      "total_awards_received": 0,
      "all_awardings": [],
      "source": "rss"
    },
    {
      "id": "oqnr6yk",
      "name": "t1_oqnr6yk",
      "author": "Sh0uldSign0ff",
      "body": "",
      "body_html": "<!-- SC_OFF --><div class=\"md\"><p>I’m just saying the experience it less money for Americans than when it’s in Europe. So obviously that will cause an increase demand for Americans, which is why these games will be sold out. It will be expensive, but my point is that’s supply and demand. How do you change that? </p> </div><!-- SC_ON -->",
      "created_utc": null,
      "created_datetime": null,
      "score": 0,
      "ups": 0,
      "downs": 0,
      "parent_id": "t3_1u0c9dc",
      "depth": 0,
      "author_flair_text": "",
      "author_flair_css_class": "",
      "author_fullname": "",
      "edited": false,
      "is_submitter": false,
      "distinguished": null,
      "stickied": false,
      "controversiality": 0,
      "total_awards_received": 0,
      "all_awardings": [],
      "source": "rss"
    },
    {
      "id": "oqnueq9",
      "name": "t1_oqnueq9",
      "author": "GetItUpYee",
      "body": "",
      "body_html": "<!-- SC_OFF --><div class=\"md\"><p>By setting prices lower. Do you think that the demand is only there because it being held in the US?</p> </div><!-- SC_ON -->",
      "created_utc": null,
      "created_datetime": null,
      "score": 0,
      "ups": 0,
      "downs": 0,
      "parent_id": "t3_1u0c9dc",
      "depth": 0,
      "author_flair_text": "",
      "author_flair_css_class": "",
      "author_fullname": "",
      "edited": false,
      "is_submitter": false,
      "distinguished": null,
      "stickied": false,
      "controversiality": 0,
      "total_awards_received": 0,
      "all_awardings": [],
      "source": "rss"
    },
    {
      "id": "oqhh5zz",
      "name": "t1_oqhh5zz",
      "author": "rmk_1808",
      "body": "",
      "body_html": "<!-- SC_OFF --><div class=\"md\"><p>Good they had subtitles or it would have been like that SNL episode with James McAvoy.</p> </div><!-- SC_ON -->",
      "created_utc": null,
      "created_datetime": null,
      "score": 0,
      "ups": 0,
      "downs": 0,
      "parent_id": "t3_1u0c9dc",
      "depth": 0,
      "author_flair_text": "",
      "author_flair_css_class": "",
      "author_fullname": "",
      "edited": false,
      "is_submitter": false,
      "distinguished": null,
      "stickied": false,
      "controversiality": 0,
      "total_awards_received": 0,
      "all_awardings": [],
      "source": "rss"
    },
    {
      "id": "oqhxtys",
      "name": "t1_oqhxtys",
      "author": "kiHrt",
      "body": "",
      "body_html": "<!-- SC_OFF --><div class=\"md\"><p>I can understand and appreciate the arguments being made here but they don't hold up to the simple math of this particular equation.</p> <p>Let's assume that of the 104 total world cup games this tournament, each stadium can hold 100k fans (they can't and the average stadium size is slightly smaller but using big round numbers here to make the math easier.)</p> <p>104 x 100k = 10.4m</p> <p>So at a maximum with every seat being filled by a unique human, this tournament could potentially service 10.4 million attendees as spectators.</p> <p>Football has hundreds of millions if not billions of fans worldwide who would love to attend these matches. Not to mention all the casuals and new fans that the growth of the game will attract with having its biggest tournament in their backyard.</p> <p>There is simply no way to allow all the fans who want to see these games live the ability to do so.</p> <p>I keep hearing complaints about the ticket prices being the reason fans can't or won't attend. Lowering those prices doesn't solve this problem, it would only exacerbate the current math issue. Cheaper tickets would create greater demand.</p> <p>There is not an easy solution. Even if ticket prices were lowered and fans could travel to the tournament location at reasonable prices, you still have the basic issue of too much demand and too little supply. Because of this, FIFA is trying to generate as much revenue as possible for all the obvious reasons.</p> <p>Were I given the task of providing the best solution to this problem, I think it starts with the various FAs putting some pressure on FIFA to hold up to their \"non-profit\" designation. Allot tickets for each group round match evenly to the two related FAs for each game and allow the respective FAs to determine the best distribution method. Lottery? Random queue? First come first serve? No scalping allowed? None of these completely solve the problem but might get closer to fan expectations for expected costs.</p> <p>Again though, the cheaper the cost to attend, the greater the demand. Additionally, the goal of FIFA and this tournament - as I've understood it - is to grow the game. Host nations need infrastructure not just for football matches but also lodging, hospitality, food, transportation. That's hard to do in undeveloped regions of the globe and easier in those places already accustomed to hosting large sporting events.</p> <p>All this to say, if this tournament were held in England, France, Spain, Brazil or anywhere, all of these current issues would still exist. No matter what, not everyone can get in and the argument of, \"the game is for the working man\" went out the window years ago with the amount of money that has been injected. Unfortunately, at its highest levels, this has become an arms race like most everything else in the world.</p> </div><!-- SC_ON -->",
      "created_utc": null,
      "created_datetime": null,
      "score": 0,
      "ups": 0,
      "downs": 0,
      "parent_id": "t3_1u0c9dc",
      "depth": 0,
      "author_flair_text": "",
      "author_flair_css_class": "",
      "author_fullname": "",
      "edited": false,
      "is_submitter": false,
      "distinguished": null,
      "stickied": false,
      "controversiality": 0,
      "total_awards_received": 0,
      "all_awardings": [],
      "source": "rss"
    },
    {
      "id": "oqhj9j7",
      "name": "t1_oqhj9j7",
      "author": "rayneeder",
      "body": "",
      "body_html": "<!-- SC_OFF --><div class=\"md\"><p>Are the matches not selling out which is causing the inflation of tickets? Were past world cups much cheaper? I just don’t get what people are asking for here</p> </div><!-- SC_ON -->",
      "created_utc": null,
      "created_datetime": null,
      "score": 0,
      "ups": 0,
      "downs": 0,
      "parent_id": "t3_1u0c9dc",
      "depth": 0,
      "author_flair_text": "",
      "author_flair_css_class": "",
      "author_fullname": "",
      "edited": false,
      "is_submitter": false,
      "distinguished": null,
      "stickied": false,
      "controversiality": 0,
      "total_awards_received": 0,
      "all_awardings": [],
      "source": "rss"
    }
  ],
  "collection_metadata": {
    "total_comments_collected": 112,
    "comment_limit_applied": "rss_max",
    "was_truncated": false,
    "harvested_at": "2026-06-10T16:03:46.532576+00:00",
    "note": "RSS mode — limited to ~500 comments, no scores/flair/parent chain"
  }
}