{
  "id": "1u2xtww",
  "name": "t3_1u2xtww",
  "title": "Franco Mastantuono & Gonzalo Garcia could leave Real Madrid this summer. The club is considering both loan & permanent transfer options. Any permanent transfer would include buyback clauses that would allow Madrid to bring the players back in the future if they fulfil their potential elsewhere",
  "selftext": "",
  "selftext_html": "",
  "content_html_raw": "  submitted by   <a href=\"https://www.reddit.com/user/DamnThatsInsaneLol\"> /u/DamnThatsInsaneLol </a> <br/> <span><a href=\"https://sports.yahoo.com/articles/real-madrid-ready-listen-offers-080000644.html\">[link]</a></span>   <span><a href=\"https://www.reddit.com/r/soccer/comments/1u2xtww/franco_mastantuono_gonzalo_garcia_could_leave/\">[comments]</a></span>",
  "author": "DamnThatsInsaneLol",
  "author_fullname": "",
  "author_flair_text": "",
  "author_flair_css_class": "",
  "link_flair_text": "",
  "link_flair_css_class": "",
  "score": 0,
  "upvote_ratio": 0.0,
  "ups": 0,
  "downs": 0,
  "num_comments": 0,
  "created_utc": 1781181329.0,
  "created_datetime": "2026-06-11T12:35:29+00:00",
  "edited": false,
  "url": "https://sports.yahoo.com/articles/real-madrid-ready-listen-offers-080000644.html",
  "permalink": "https://www.reddit.com/r/soccer/comments/1u2xtww/franco_mastantuono_gonzalo_garcia_could_leave/",
  "domain": "",
  "is_self": false,
  "is_video": false,
  "is_original_content": false,
  "over_18": false,
  "spoiler": false,
  "stickied": false,
  "distinguished": null,
  "num_crossposts": 0,
  "crosspost_parent": null,
  "total_awards_received": 0,
  "all_awardings": [],
  "thumbnail": "",
  "is_match_thread": false,
  "media_urls": [
    {
      "url": "https://sports.yahoo.com/articles/real-madrid-ready-listen-offers-080000644.html",
      "source": "external_link",
      "type": "link",
      "verified": true,
      "status_code": 200,
      "content_type": "text/html; charset=utf-8",
      "content_length": "",
      "final_url": "https://sports.yahoo.com/articles/real-madrid-ready-listen-offers-080000644.html"
    }
  ],
  "source": "rss",
  "t0_snapshot": {
    "collected_at": "2026-06-11T12:35:42.357876+00:00",
    "batch_id": "2026-06-11T12:35",
    "score": 0,
    "upvote_ratio": 0.0,
    "num_comments": 0,
    "author_flair_text": "",
    "link_flair_text": "",
    "edited": false,
    "note": "RSS mode — scores/flair unavailable at scan time"
  },
  "t48_snapshot": null,
  "comments": [],
  "collection_metadata": null
}