{
  "all_awardings": [],
  "allow_live_comments": false,
  "approved_at_utc": null,
  "approved_by": null,
  "archived": false,
  "author": "cocacolapepsifanta",
  "author_flair_background_color": "transparent",
  "author_flair_css_class": null,
  "author_flair_richtext": [
    {
      "a": ":Portugal:",
      "e": "emoji",
      "u": "https://emoji.redditmedia.com/ur5evymf2c3h1_t5_2qi58/Portugal"
    }
  ],
  "author_flair_template_id": "a8ad979e-7c07-11e9-b588-0e55aa3940a6",
  "author_flair_text": ":Portugal:",
  "author_flair_text_color": "dark",
  "author_flair_type": "richtext",
  "author_fullname": "t2_2b02p8l9hv",
  "author_is_blocked": false,
  "author_patreon_flair": false,
  "author_premium": false,
  "awarders": [],
  "banned_at_utc": null,
  "banned_by": null,
  "can_gild": false,
  "can_mod_post": false,
  "category": null,
  "clicked": false,
  "content_categories": null,
  "contest_mode": false,
  "created": 1781284329,
  "created_utc": 1781284329,
  "discussion_type": null,
  "distinguished": null,
  "domain": "v.redd.it",
  "downs": 0,
  "edited": false,
  "gilded": 0,
  "gildings": {},
  "hidden": false,
  "hide_score": true,
  "id": "1u41fas",
  "is_created_from_ads_ui": false,
  "is_crosspostable": true,
  "is_meta": false,
  "is_original_content": false,
  "is_reddit_media_domain": true,
  "is_robot_indexable": true,
  "is_self": false,
  "is_video": true,
  "likes": null,
  "link_flair_background_color": "#4a67e8",
  "link_flair_css_class": null,
  "link_flair_richtext": [
    {
      "a": ":n_media:",
      "e": "emoji",
      "u": "https://emoji.redditmedia.com/mh67o006pb5h1_t5_2qi58/n_media"
    },
    {
      "e": "text",
      "t": " Media"
    }
  ],
  "link_flair_template_id": "9d87c07e-607a-11f1-9916-dad816529801",
  "link_flair_text": ":n_media: Media",
  "link_flair_text_color": "light",
  "link_flair_type": "richtext",
  "locked": false,
  "media": {
    "reddit_video": {
      "bitrate_kbps": 5000,
      "fallback_url": "https://v.redd.it/a9wbq5mswv6h1/CMAF_1080.mp4?source=fallback",
      "has_audio": true,
      "height": 1080,
      "width": 1920,
      "scrubber_media_url": "https://v.redd.it/a9wbq5mswv6h1/CMAF_96.mp4",
      "dash_url": "https://v.redd.it/a9wbq5mswv6h1/DASHPlaylist.mpd?a=1783876346%2CNzc2N2VlMjFiODc5NmRlNTE2NDlmZTcyM2E4ZmJhN2ZiMjQ1NGM1NjI3MjhlNjM1NGRiZDUyOTJjZjkxMWQyYw%3D%3D&v=1&f=sd",
      "duration": 22,
      "hls_url": "https://v.redd.it/a9wbq5mswv6h1/HLSPlaylist.m3u8?a=1783876346%2CNzAwYzdlODhhYzE4YzA4MDM3MTFlNTM3YmFhZWQ2ZGM1OGRjY2Y1NTNiNTg3OTM0ZWMyMzBhYTk2NjFmZDI0Yg%3D%3D&v=1&f=sd",
      "is_gif": false,
      "transcoding_status": "completed"
    }
  },
  "media_embed": {},
  "media_only": false,
  "mod_note": null,
  "mod_reason_by": null,
  "mod_reason_title": null,
  "mod_reports": [],
  "name": "t3_1u41fas",
  "no_follow": true,
  "num_comments": 1,
  "num_crossposts": 0,
  "num_reports": null,
  "over_18": false,
  "permalink": "/r/soccer/comments/1u41fas/the_energy_in_toronto_right_now_is_insane/",
  "pinned": false,
  "post_hint": "hosted:video",
  "preview": {
    "images": [
      {
        "source": {
          "url": "https://external-preview.redd.it/dmZpMzR4bnN3djZoMfZ0D3u8QjQ4RPfrrfZfeBl_659HuwmsmxnvAhsCV_80.png?format=pjpg&auto=webp&s=592c57c642b46fabb99e8d7af9a06958c37b9a67",
          "width": 1920,
          "height": 1080
        },
        "resolutions": [
          {
            "url": "https://external-preview.redd.it/dmZpMzR4bnN3djZoMfZ0D3u8QjQ4RPfrrfZfeBl_659HuwmsmxnvAhsCV_80.png?width=108&crop=smart&format=pjpg&auto=webp&s=cd5b4bd8c6f087c8dc81e813963b9746bac17c6f",
            "width": 108,
            "height": 60
          },
          {
            "url": "https://external-preview.redd.it/dmZpMzR4bnN3djZoMfZ0D3u8QjQ4RPfrrfZfeBl_659HuwmsmxnvAhsCV_80.png?width=216&crop=smart&format=pjpg&auto=webp&s=ba80b0ddf4a98a62d74367350137e2a541ebe970",
            "width": 216,
            "height": 121
          },
          {
            "url": "https://external-preview.redd.it/dmZpMzR4bnN3djZoMfZ0D3u8QjQ4RPfrrfZfeBl_659HuwmsmxnvAhsCV_80.png?width=320&crop=smart&format=pjpg&auto=webp&s=bb79b7f34dbcc817507a4daa87f3d95ae881b186",
            "width": 320,
            "height": 180
          },
          {
            "url": "https://external-preview.redd.it/dmZpMzR4bnN3djZoMfZ0D3u8QjQ4RPfrrfZfeBl_659HuwmsmxnvAhsCV_80.png?width=640&crop=smart&format=pjpg&auto=webp&s=a36f0b6be254bec00f26eba26cfbd624fbea9cbc",
            "width": 640,
            "height": 360
          },
          {
            "url": "https://external-preview.redd.it/dmZpMzR4bnN3djZoMfZ0D3u8QjQ4RPfrrfZfeBl_659HuwmsmxnvAhsCV_80.png?width=960&crop=smart&format=pjpg&auto=webp&s=0fe809566c7dc723aad4963a39885c8bdd9ee682",
            "width": 960,
            "height": 540
          },
          {
            "url": "https://external-preview.redd.it/dmZpMzR4bnN3djZoMfZ0D3u8QjQ4RPfrrfZfeBl_659HuwmsmxnvAhsCV_80.png?width=1080&crop=smart&format=pjpg&auto=webp&s=3a5fb20f2e95132782510dfb472209e07a11ac34",
            "width": 1080,
            "height": 607
          }
        ],
        "variants": {},
        "id": "dmZpMzR4bnN3djZoMfZ0D3u8QjQ4RPfrrfZfeBl_659HuwmsmxnvAhsCV_80"
      }
    ],
    "enabled": false
  },
  "pwls": 6,
  "quarantine": false,
  "removal_reason": null,
  "removed_by": null,
  "removed_by_category": null,
  "report_reasons": null,
  "retrieved_on": 1781284348,
  "saved": false,
  "score": 0,
  "secure_media": {
    "reddit_video": {
      "bitrate_kbps": 5000,
      "fallback_url": "https://v.redd.it/a9wbq5mswv6h1/CMAF_1080.mp4?source=fallback",
      "has_audio": true,
      "height": 1080,
      "width": 1920,
      "scrubber_media_url": "https://v.redd.it/a9wbq5mswv6h1/CMAF_96.mp4",
      "dash_url": "https://v.redd.it/a9wbq5mswv6h1/DASHPlaylist.mpd?a=1783876346%2CNzc2N2VlMjFiODc5NmRlNTE2NDlmZTcyM2E4ZmJhN2ZiMjQ1NGM1NjI3MjhlNjM1NGRiZDUyOTJjZjkxMWQyYw%3D%3D&v=1&f=sd",
      "duration": 22,
      "hls_url": "https://v.redd.it/a9wbq5mswv6h1/HLSPlaylist.m3u8?a=1783876346%2CNzAwYzdlODhhYzE4YzA4MDM3MTFlNTM3YmFhZWQ2ZGM1OGRjY2Y1NTNiNTg3OTM0ZWMyMzBhYTk2NjFmZDI0Yg%3D%3D&v=1&f=sd",
      "is_gif": false,
      "transcoding_status": "completed"
    }
  },
  "secure_media_embed": {},
  "selftext": "",
  "send_replies": true,
  "spoiler": false,
  "stickied": false,
  "subreddit": "soccer",
  "subreddit_id": "t5_2qi58",
  "subreddit_name_prefixed": "r/soccer",
  "subreddit_subscribers": 8662556,
  "subreddit_type": "public",
  "suggested_sort": null,
  "thumbnail": "default",
  "thumbnail_height": 78,
  "thumbnail_width": 140,
  "title": "The energy in Toronto right now is insane! Thousands marching to the stadium for Canada’s World Cup debut!",
  "top_awarded_type": null,
  "total_awards_received": 0,
  "treatment_tags": [],
  "ups": 0,
  "upvote_ratio": 0.5,
  "url": "https://v.redd.it/a9wbq5mswv6h1",
  "url_overridden_by_dest": "https://v.redd.it/a9wbq5mswv6h1",
  "user_reports": [],
  "view_count": null,
  "visited": false,
  "wls": 6,
  "is_match_thread": false,
  "media_urls": [
    {
      "url": "https://v.redd.it/a9wbq5mswv6h1/CMAF_1080.mp4?source=fallback",
      "source": "reddit_video",
      "type": "video",
      "downloaded": true,
      "local_path": "data/media/1u41fas/media_38720072.mp4",
      "file_size_bytes": 14389425,
      "content_type": "video/mp4"
    },
    {
      "url": "https://external-preview.redd.it/dmZpMzR4bnN3djZoMfZ0D3u8QjQ4RPfrrfZfeBl_659HuwmsmxnvAhsCV_80.png?format=pjpg&auto=webp&s=592c57c642b46fabb99e8d7af9a06958c37b9a67",
      "source": "preview",
      "type": "image"
    },
    {
      "url": "https://v.redd.it/a9wbq5mswv6h1",
      "source": "post_url",
      "type": "video",
      "downloaded": false,
      "reason": "403 Client Error: Blocked for url: https://www.reddit.com/video/a9wbq5mswv6h1"
    }
  ],
  "source": "merged",
  "t0_snapshot": {
    "collected_at": "2026-06-12T17:16:08.236286+00:00",
    "batch_id": "2026-06-12T17:16",
    "score": 0,
    "upvote_ratio": 0.5,
    "num_comments": 1,
    "author_flair_text": ":Portugal:",
    "link_flair_text": ":n_media: Media",
    "edited": false
  },
  "t48_snapshot": null,
  "comments": [],
  "collection_metadata": null,
  "rss_content_html_raw": "  submitted by   <a href=\"https://www.reddit.com/user/cocacolapepsifanta\"> /u/cocacolapepsifanta </a> <br/> <span><a href=\"https://v.redd.it/a9wbq5mswv6h1\">[link]</a></span>   <span><a href=\"https://www.reddit.com/r/soccer/comments/1u41fas/the_energy_in_toronto_right_now_is_insane/\">[comments]</a></span>"
}